{
    "$schema": "https://hbidvanalyticsweb.z20.web.core.windows.net/schema/processPayload/schema/payload.schema.json",
    "processId": 20006,
    "parentProcessId": null,
    "displayName": "FactFGInventoryAvailability_StageToSynapse",
    "processType": "Data",
    "dataFactoryInstance": "01",
    "pipelineName": "common_driver_stage_to_synapse",
    "isActive": true,
    "configurationPayload": {
        "processPayload": [
            {
                "processSystem": "databricks",
                "processType": "notebook",
                "label": "Staging Ingest -> Curated",
                "processConfig": {
                    "notebookPath": "/Common/01/Workflows/Pipelines/Curated/FactFGInventoryAvailability/FactFGInventoryAvailabilityDriver",
                    "linkedService": {
                        "jobComplexity": "simple",
                        "jobSize": "small",
                        "clusterConfig": {
                            "workerType": "Standard_F4s",
                            "workers": "4",
                            "driverType": "Standard_F4s"
                        }
                    }
                }
            },
            {
                "processSystem": "databricks",
                "processType": "notebook",
                "label": "Curated -> Synapse",
                "processConfig": {
                    "notebookPath": "/Common/DataPlatform/Workflows/Pipelines/Synapse/Common/common_curated_to_synapse",
                    "linkedService": {
                        "jobComplexity": "simple",
                        "jobSize": "small",
                        "clusterConfig": {
                            "workerType": "Standard_F4s",
                            "workers": "4",
                            "driverType": "Standard_F4s"
                        }
                    }
                }
            },
            {
                "processSystem": "databricks",
                "processType": "notebook",
                "label": "Curated Ingest -> Curated Archive",
                "processConfig": {
                    "notebookPath": "/Common/DataPlatform/Workflows/Pipelines/Curated/Common/common_curated_ingest_to_archive",
                    "linkedService": {
                        "jobComplexity": "simple",
                        "jobSize": "small",
                        "clusterConfig": {
                            "workerType": "Standard_F4s",
                            "workers": "4",
                            "driverType": "Standard_F4s"
                        }
                    }
                }
            }
        ],
        "dataPayload": [
            {
                "label": "Curated Ingest Source",
                "dataSystem": "databricks",
                "dataSource": "delta",
                "dataConfig": {
                    "path": "/mnt/curated/Inventory/US/SAP/FactFGInventoryAvailability/Ingest"
                }
            },
            {
                "label": "Curated Archive Sink",
                "dataSystem": "databricks",
                "dataSource": "delta",
                "dataConfig": {
                    "path": "/mnt/curated/Inventory/US/SAP/FactFGInventoryAvailability/Archive",
                    "mergeColumns": [
                        "InventoryAvailabilityKey"
                    ]
                }
            },
            {
                "label": "Synapse Sink",
                "dataSystem": "databricks",
                "dataSource": "Synapse",
                "dataConfig": {
                    "synapseTable": "stage.FactFGInventoryAvailability",
                    "tempContainer": "synapse",
                    "tempDirectory": "Inventory/FactFGInventoryAvailability",
                    "mergeProcedure": "Common.LoadFactFGInventoryAvailability",
                    "maxStrLen": "350"
                }
            }
        ]
    }
}