<?xml version="1.0" encoding="Windows-1252"?>
<!DOCTYPE POWERMART SYSTEM "powrmart.dtd">
<POWERMART CREATION_DATE="10/09/2024 09:55:29" REPOSITORY_VERSION="187.96">
<REPOSITORY NAME="Domain10_Rep_Svc_Prd" VERSION="187" CODEPAGE="MS1252" DATABASETYPE="Microsoft SQL Server">
<FOLDER NAME="SUPPLY_CHAIN_BI" GROUP="" OWNER="Administrator" SHARED="NOTSHARED" DESCRIPTION="" PERMISSIONS="rwx---r--" UUID="c048e0d4-8833-4f61-bdc8-10cb41aa67f1">
    <SOURCE BUSINESSNAME ="" DATABASETYPE ="Flat File" DBDNAME ="Flat_File" DESCRIPTION ="This is the flat file Teklynx.dat (Fixed length width flat file)" NAME ="FF_TEKLYNX" OBJECTVERSION ="1" OWNERNAME ="" VERSIONNUMBER ="1">
        <FLATFILE CODEPAGE ="MS1252" CONSECDELIMITERSASONE ="NO" DELIMITED ="NO" DELIMITERS ="," ESCAPE_CHARACTER ="" KEEPESCAPECHAR ="NO" LINESEQUENTIAL ="NO" MULTIDELIMITERSASAND ="NO" NULLCHARTYPE ="ASCII" NULL_CHARACTER ="*" PADBYTES ="0" QUOTE_CHARACTER ="DOUBLE" REPEATABLE ="NO" ROWDELIMITER ="0" SHIFTSENSITIVEDATA ="NO" SKIPROWS ="0" STRIPTRAILINGBLANKS ="NO"/>
        <TABLEATTRIBUTE NAME ="Base Table Name" VALUE =""/>
        <TABLEATTRIBUTE NAME ="Search Specification" VALUE =""/>
        <TABLEATTRIBUTE NAME ="Sort Specification" VALUE =""/>
        <TABLEATTRIBUTE NAME ="Datetime Format" VALUE ="A  19 mm/dd/yyyy hh24:mi:ss"/>
        <TABLEATTRIBUTE NAME ="Thousand Separator" VALUE ="None"/>
        <TABLEATTRIBUTE NAME ="Decimal Separator" VALUE ="."/>
        <TABLEATTRIBUTE NAME ="Add Currently Processed Flat File Name Port" VALUE ="NO"/>
        <TABLEATTRIBUTE NAME ="Source TimeStamp" VALUE =""/>
        <SOURCEFIELD BUSINESSNAME ="" DATATYPE ="string" DESCRIPTION ="" FIELDNUMBER ="1" FIELDPROPERTY ="0" FIELDTYPE ="ELEMITEM" HIDDEN ="NO" KEYTYPE ="NOT A KEY" LENGTH ="40" LEVEL ="0" NAME ="Key" NULLABLE ="NULL" OCCURS ="0" OFFSET ="0" PHYSICALLENGTH ="40" PHYSICALOFFSET ="0" PICTURETEXT ="" PRECISION ="40" SCALE ="0" USAGE_FLAGS =""/>
        <SOURCEFIELD BUSINESSNAME ="" DATATYPE ="string" DESCRIPTION ="" FIELDNUMBER ="2" FIELDPROPERTY ="0" FIELDTYPE ="ELEMITEM" HIDDEN ="NO" KEYTYPE ="NOT A KEY" LENGTH ="2" LEVEL ="0" NAME ="division" NULLABLE ="NULL" OCCURS ="0" OFFSET ="40" PHYSICALLENGTH ="2" PHYSICALOFFSET ="40" PICTURETEXT ="" PRECISION ="2" SCALE ="0" USAGE_FLAGS =""/>
        <SOURCEFIELD BUSINESSNAME ="" DATATYPE ="string" DESCRIPTION ="" FIELDNUMBER ="3" FIELDPROPERTY ="0" FIELDTYPE ="ELEMITEM" HIDDEN ="NO" KEYTYPE ="NOT A KEY" LENGTH ="4" LEVEL ="0" NAME ="product_line" NULLABLE ="NULL" OCCURS ="0" OFFSET ="42" PHYSICALLENGTH ="4" PHYSICALOFFSET ="42" PICTURETEXT ="" PRECISION ="4" SCALE ="0" USAGE_FLAGS =""/>
        <SOURCEFIELD BUSINESSNAME ="" DATATYPE ="string" DESCRIPTION ="" FIELDNUMBER ="4" FIELDPROPERTY ="0" FIELDTYPE ="ELEMITEM" HIDDEN ="NO" KEYTYPE ="NOT A KEY" LENGTH ="20" LEVEL ="0" NAME ="product_name" NULLABLE ="NULL" OCCURS ="0" OFFSET ="46" PHYSICALLENGTH ="20" PHYSICALOFFSET ="46" PICTURETEXT ="" PRECISION ="20" SCALE ="0" USAGE_FLAGS =""/>
        <SOURCEFIELD BUSINESSNAME ="" DATATYPE ="string" DESCRIPTION ="" FIELDNUMBER ="5" FIELDPROPERTY ="0" FIELDTYPE ="ELEMITEM" HIDDEN ="NO" KEYTYPE ="NOT A KEY" LENGTH ="8" LEVEL ="0" NAME ="style" NULLABLE ="NULL" OCCURS ="0" OFFSET ="66" PHYSICALLENGTH ="8" PHYSICALOFFSET ="66" PICTURETEXT ="" PRECISION ="8" SCALE ="0" USAGE_FLAGS =""/>
        <SOURCEFIELD BUSINESSNAME ="" DATATYPE ="string" DESCRIPTION ="" FIELDNUMBER ="6" FIELDPROPERTY ="0" FIELDTYPE ="ELEMITEM" HIDDEN ="NO" KEYTYPE ="NOT A KEY" LENGTH ="35" LEVEL ="0" NAME ="style_desc" NULLABLE ="NULL" OCCURS ="0" OFFSET ="74" PHYSICALLENGTH ="35" PHYSICALOFFSET ="74" PICTURETEXT ="" PRECISION ="35" SCALE ="0" USAGE_FLAGS =""/>
        <SOURCEFIELD BUSINESSNAME ="" DATATYPE ="string" DESCRIPTION ="" FIELDNUMBER ="7" FIELDPROPERTY ="0" FIELDTYPE ="ELEMITEM" HIDDEN ="NO" KEYTYPE ="NOT A KEY" LENGTH ="30" LEVEL ="0" NAME ="alt_style" NULLABLE ="NULL" OCCURS ="0" OFFSET ="109" PHYSICALLENGTH ="30" PHYSICALOFFSET ="109" PICTURETEXT ="" PRECISION ="30" SCALE ="0" USAGE_FLAGS =""/>
        <SOURCEFIELD BUSINESSNAME ="" DATATYPE ="string" DESCRIPTION ="" FIELDNUMBER ="8" FIELDPROPERTY ="0" FIELDTYPE ="ELEMITEM" HIDDEN ="NO" KEYTYPE ="NOT A KEY" LENGTH ="4" LEVEL ="0" NAME ="color" NULLABLE ="NULL" OCCURS ="0" OFFSET ="139" PHYSICALLENGTH ="4" PHYSICALOFFSET ="139" PICTURETEXT ="" PRECISION ="4" SCALE ="0" USAGE_FLAGS =""/>
        <SOURCEFIELD BUSINESSNAME ="" DATATYPE ="string" DESCRIPTION ="" FIELDNUMBER ="9" FIELDPROPERTY ="0" FIELDTYPE ="ELEMITEM" HIDDEN ="NO" KEYTYPE ="NOT A KEY" LENGTH ="35" LEVEL ="0" NAME ="color_desc" NULLABLE ="NULL" OCCURS ="0" OFFSET ="143" PHYSICALLENGTH ="35" PHYSICALOFFSET ="143" PICTURETEXT ="" PRECISION ="35" SCALE ="0" USAGE_FLAGS =""/>
        <SOURCEFIELD BUSINESSNAME ="" DATATYPE ="string" DESCRIPTION ="" FIELDNUMBER ="10" FIELDPROPERTY ="0" FIELDTYPE ="ELEMITEM" HIDDEN ="NO" KEYTYPE ="NOT A KEY" LENGTH ="30" LEVEL ="0" NAME ="alt_color" NULLABLE ="NULL" OCCURS ="0" OFFSET ="178" PHYSICALLENGTH ="30" PHYSICALOFFSET ="178" PICTURETEXT ="" PRECISION ="30" SCALE ="0" USAGE_FLAGS =""/>
        <SOURCEFIELD BUSINESSNAME ="" DATATYPE ="string" DESCRIPTION ="" FIELDNUMBER ="11" FIELDPROPERTY ="0" FIELDTYPE ="ELEMITEM" HIDDEN ="NO" KEYTYPE ="NOT A KEY" LENGTH ="5" LEVEL ="0" NAME ="size_cd" NULLABLE ="NULL" OCCURS ="0" OFFSET ="208" PHYSICALLENGTH ="5" PHYSICALOFFSET ="208" PICTURETEXT ="" PRECISION ="5" SCALE ="0" USAGE_FLAGS =""/>
        <SOURCEFIELD BUSINESSNAME ="" DATATYPE ="string" DESCRIPTION ="" FIELDNUMBER ="12" FIELDPROPERTY ="0" FIELDTYPE ="ELEMITEM" HIDDEN ="NO" KEYTYPE ="NOT A KEY" LENGTH ="35" LEVEL ="0" NAME ="size_desc" NULLABLE ="NULL" OCCURS ="0" OFFSET ="213" PHYSICALLENGTH ="35" PHYSICALOFFSET ="213" PICTURETEXT ="" PRECISION ="35" SCALE ="0" USAGE_FLAGS =""/>
        <SOURCEFIELD BUSINESSNAME ="" DATATYPE ="string" DESCRIPTION ="" FIELDNUMBER ="13" FIELDPROPERTY ="0" FIELDTYPE ="ELEMITEM" HIDDEN ="NO" KEYTYPE ="NOT A KEY" LENGTH ="30" LEVEL ="0" NAME ="alt_size1_cd" NULLABLE ="NULL" OCCURS ="0" OFFSET ="248" PHYSICALLENGTH ="30" PHYSICALOFFSET ="248" PICTURETEXT ="" PRECISION ="30" SCALE ="0" USAGE_FLAGS =""/>
        <SOURCEFIELD BUSINESSNAME ="" DATATYPE ="string" DESCRIPTION ="" FIELDNUMBER ="14" FIELDPROPERTY ="0" FIELDTYPE ="ELEMITEM" HIDDEN ="NO" KEYTYPE ="NOT A KEY" LENGTH ="30" LEVEL ="0" NAME ="cup" NULLABLE ="NULL" OCCURS ="0" OFFSET ="278" PHYSICALLENGTH ="30" PHYSICALOFFSET ="278" PICTURETEXT ="" PRECISION ="30" SCALE ="0" USAGE_FLAGS =""/>
        <SOURCEFIELD BUSINESSNAME ="" DATATYPE ="string" DESCRIPTION ="" FIELDNUMBER ="15" FIELDPROPERTY ="0" FIELDTYPE ="ELEMITEM" HIDDEN ="NO" KEYTYPE ="NOT A KEY" LENGTH ="18" LEVEL ="0" NAME ="upc_cd" NULLABLE ="NULL" OCCURS ="0" OFFSET ="308" PHYSICALLENGTH ="18" PHYSICALOFFSET ="308" PICTURETEXT ="" PRECISION ="18" SCALE ="0" USAGE_FLAGS =""/>
        <SOURCEFIELD BUSINESSNAME ="" DATATYPE ="string" DESCRIPTION ="" FIELDNUMBER ="16" FIELDPROPERTY ="0" FIELDTYPE ="ELEMITEM" HIDDEN ="NO" KEYTYPE ="NOT A KEY" LENGTH ="6" LEVEL ="0" NAME ="attribute_cd" NULLABLE ="NULL" OCCURS ="0" OFFSET ="326" PHYSICALLENGTH ="6" PHYSICALOFFSET ="326" PICTURETEXT ="" PRECISION ="6" SCALE ="0" USAGE_FLAGS =""/>
        <SOURCEFIELD BUSINESSNAME ="" DATATYPE ="string" DESCRIPTION ="" FIELDNUMBER ="17" FIELDPROPERTY ="0" FIELDTYPE ="ELEMITEM" HIDDEN ="NO" KEYTYPE ="NOT A KEY" LENGTH ="3" LEVEL ="0" NAME ="putup" NULLABLE ="NULL" OCCURS ="0" OFFSET ="332" PHYSICALLENGTH ="3" PHYSICALOFFSET ="332" PICTURETEXT ="" PRECISION ="3" SCALE ="0" USAGE_FLAGS =""/>
        <SOURCEFIELD BUSINESSNAME ="" DATATYPE ="string" DESCRIPTION ="" FIELDNUMBER ="18" FIELDPROPERTY ="0" FIELDTYPE ="ELEMITEM" HIDDEN ="NO" KEYTYPE ="NOT A KEY" LENGTH ="11" LEVEL ="0" NAME ="retail_price" NULLABLE ="NULL" OCCURS ="0" OFFSET ="335" PHYSICALLENGTH ="11" PHYSICALOFFSET ="335" PICTURETEXT ="" PRECISION ="11" SCALE ="0" USAGE_FLAGS =""/>
        <SOURCEFIELD BUSINESSNAME ="" DATATYPE ="string" DESCRIPTION ="" FIELDNUMBER ="19" FIELDPROPERTY ="0" FIELDTYPE ="ELEMITEM" HIDDEN ="NO" KEYTYPE ="NOT A KEY" LENGTH ="20" LEVEL ="0" NAME ="multiple_price" NULLABLE ="NULL" OCCURS ="0" OFFSET ="346" PHYSICALLENGTH ="20" PHYSICALOFFSET ="346" PICTURETEXT ="" PRECISION ="20" SCALE ="0" USAGE_FLAGS =""/>
        <SOURCEFIELD BUSINESSNAME ="" DATATYPE ="string" DESCRIPTION ="" FIELDNUMBER ="20" FIELDPROPERTY ="0" FIELDTYPE ="ELEMITEM" HIDDEN ="NO" KEYTYPE ="NOT A KEY" LENGTH ="5" LEVEL ="0" NAME ="currency" NULLABLE ="NULL" OCCURS ="0" OFFSET ="366" PHYSICALLENGTH ="5" PHYSICALOFFSET ="366" PICTURETEXT ="" PRECISION ="5" SCALE ="0" USAGE_FLAGS =""/>
        <SOURCEFIELD BUSINESSNAME ="" DATATYPE ="string" DESCRIPTION ="" FIELDNUMBER ="21" FIELDPROPERTY ="0" FIELDTYPE ="ELEMITEM" HIDDEN ="NO" KEYTYPE ="NOT A KEY" LENGTH ="8" LEVEL ="0" NAME ="price_eff_dt" NULLABLE ="NULL" OCCURS ="0" OFFSET ="371" PHYSICALLENGTH ="8" PHYSICALOFFSET ="371" PICTURETEXT ="" PRECISION ="8" SCALE ="0" USAGE_FLAGS =""/>
        <SOURCEFIELD BUSINESSNAME ="" DATATYPE ="string" DESCRIPTION ="" FIELDNUMBER ="22" FIELDPROPERTY ="0" FIELDTYPE ="ELEMITEM" HIDDEN ="NO" KEYTYPE ="NOT A KEY" LENGTH ="10" LEVEL ="0" NAME ="dept" NULLABLE ="NULL" OCCURS ="0" OFFSET ="379" PHYSICALLENGTH ="10" PHYSICALOFFSET ="379" PICTURETEXT ="" PRECISION ="10" SCALE ="0" USAGE_FLAGS =""/>
        <SOURCEFIELD BUSINESSNAME ="" DATATYPE ="string" DESCRIPTION ="" FIELDNUMBER ="23" FIELDPROPERTY ="0" FIELDTYPE ="ELEMITEM" HIDDEN ="NO" KEYTYPE ="NOT A KEY" LENGTH ="35" LEVEL ="0" NAME ="cust_sku" NULLABLE ="NULL" OCCURS ="0" OFFSET ="389" PHYSICALLENGTH ="35" PHYSICALOFFSET ="389" PICTURETEXT ="" PRECISION ="35" SCALE ="0" USAGE_FLAGS =""/>
        <SOURCEFIELD BUSINESSNAME ="" DATATYPE ="string" DESCRIPTION ="" FIELDNUMBER ="24" FIELDPROPERTY ="0" FIELDTYPE ="ELEMITEM" HIDDEN ="NO" KEYTYPE ="NOT A KEY" LENGTH ="10" LEVEL ="0" NAME ="cust_nbr" NULLABLE ="NULL" OCCURS ="0" OFFSET ="424" PHYSICALLENGTH ="10" PHYSICALOFFSET ="424" PICTURETEXT ="" PRECISION ="10" SCALE ="0" USAGE_FLAGS =""/>
        <SOURCEFIELD BUSINESSNAME ="" DATATYPE ="string" DESCRIPTION ="" FIELDNUMBER ="25" FIELDPROPERTY ="0" FIELDTYPE ="ELEMITEM" HIDDEN ="NO" KEYTYPE ="NOT A KEY" LENGTH ="35" LEVEL ="0" NAME ="cust_name" NULLABLE ="NULL" OCCURS ="0" OFFSET ="434" PHYSICALLENGTH ="35" PHYSICALOFFSET ="434" PICTURETEXT ="" PRECISION ="35" SCALE ="0" USAGE_FLAGS =""/>
        <SOURCEFIELD BUSINESSNAME ="" DATATYPE ="string" DESCRIPTION ="" FIELDNUMBER ="26" FIELDPROPERTY ="0" FIELDTYPE ="ELEMITEM" HIDDEN ="NO" KEYTYPE ="NOT A KEY" LENGTH ="18" LEVEL ="0" NAME ="material" NULLABLE ="NULL" OCCURS ="0" OFFSET ="469" PHYSICALLENGTH ="18" PHYSICALOFFSET ="469" PICTURETEXT ="" PRECISION ="18" SCALE ="0" USAGE_FLAGS =""/>
        <SOURCEFIELD BUSINESSNAME ="" DATATYPE ="string" DESCRIPTION ="" FIELDNUMBER ="27" FIELDPROPERTY ="0" FIELDTYPE ="ELEMITEM" HIDDEN ="NO" KEYTYPE ="NOT A KEY" LENGTH ="8" LEVEL ="0" NAME ="grid" NULLABLE ="NULL" OCCURS ="0" OFFSET ="487" PHYSICALLENGTH ="8" PHYSICALOFFSET ="487" PICTURETEXT ="" PRECISION ="8" SCALE ="0" USAGE_FLAGS =""/>
        <SOURCEFIELD BUSINESSNAME ="" DATATYPE ="string" DESCRIPTION ="" FIELDNUMBER ="28" FIELDPROPERTY ="0" FIELDTYPE ="ELEMITEM" HIDDEN ="NO" KEYTYPE ="NOT A KEY" LENGTH ="15" LEVEL ="0" NAME ="timestamp" NULLABLE ="NULL" OCCURS ="0" OFFSET ="495" PHYSICALLENGTH ="15" PHYSICALOFFSET ="495" PICTURETEXT ="" PRECISION ="15" SCALE ="0" USAGE_FLAGS =""/>
    </SOURCE>
    <TARGET BUSINESSNAME ="Teklynx_SAP_data" CONSTRAINT ="" DATABASETYPE ="Microsoft SQL Server" DESCRIPTION ="Target table deifinition" NAME ="Teklynx_SAP_data" OBJECTVERSION ="1" TABLEOPTIONS ="" VERSIONNUMBER ="1">
        <TARGETFIELD BUSINESSNAME ="" DATATYPE ="varchar" DESCRIPTION ="" FIELDNUMBER ="1" KEYTYPE ="NOT A KEY" NAME ="Hbi_key" NULLABLE ="NULL" PICTURETEXT ="" PRECISION ="40" SCALE ="0"/>
        <TARGETFIELD BUSINESSNAME ="" DATATYPE ="varchar" DESCRIPTION ="" FIELDNUMBER ="2" KEYTYPE ="NOT A KEY" NAME ="SAP_division" NULLABLE ="NULL" PICTURETEXT ="" PRECISION ="2" SCALE ="0"/>
        <TARGETFIELD BUSINESSNAME ="" DATATYPE ="varchar" DESCRIPTION ="" FIELDNUMBER ="3" KEYTYPE ="NOT A KEY" NAME ="product_line" NULLABLE ="NULL" PICTURETEXT ="" PRECISION ="4" SCALE ="0"/>
        <TARGETFIELD BUSINESSNAME ="" DATATYPE ="varchar" DESCRIPTION ="" FIELDNUMBER ="4" KEYTYPE ="NOT A KEY" NAME ="product_name" NULLABLE ="NULL" PICTURETEXT ="" PRECISION ="20" SCALE ="0"/>
        <TARGETFIELD BUSINESSNAME ="" DATATYPE ="varchar" DESCRIPTION ="" FIELDNUMBER ="5" KEYTYPE ="NOT A KEY" NAME ="style" NULLABLE ="NULL" PICTURETEXT ="" PRECISION ="8" SCALE ="0"/>
        <TARGETFIELD BUSINESSNAME ="" DATATYPE ="varchar" DESCRIPTION ="" FIELDNUMBER ="6" KEYTYPE ="NOT A KEY" NAME ="Style_Description" NULLABLE ="NULL" PICTURETEXT ="" PRECISION ="35" SCALE ="0"/>
        <TARGETFIELD BUSINESSNAME ="" DATATYPE ="varchar" DESCRIPTION ="" FIELDNUMBER ="7" KEYTYPE ="NOT A KEY" NAME ="Legacy_Style" NULLABLE ="NULL" PICTURETEXT ="" PRECISION ="30" SCALE ="0"/>
        <TARGETFIELD BUSINESSNAME ="" DATATYPE ="varchar" DESCRIPTION ="" FIELDNUMBER ="8" KEYTYPE ="NOT A KEY" NAME ="color" NULLABLE ="NULL" PICTURETEXT ="" PRECISION ="4" SCALE ="0"/>
        <TARGETFIELD BUSINESSNAME ="" DATATYPE ="varchar" DESCRIPTION ="" FIELDNUMBER ="9" KEYTYPE ="NOT A KEY" NAME ="color_description" NULLABLE ="NULL" PICTURETEXT ="" PRECISION ="35" SCALE ="0"/>
        <TARGETFIELD BUSINESSNAME ="" DATATYPE ="varchar" DESCRIPTION ="" FIELDNUMBER ="10" KEYTYPE ="NOT A KEY" NAME ="Legacy_Color" NULLABLE ="NULL" PICTURETEXT ="" PRECISION ="30" SCALE ="0"/>
        <TARGETFIELD BUSINESSNAME ="" DATATYPE ="varchar" DESCRIPTION ="" FIELDNUMBER ="11" KEYTYPE ="NOT A KEY" NAME ="size" NULLABLE ="NULL" PICTURETEXT ="" PRECISION ="5" SCALE ="0"/>
        <TARGETFIELD BUSINESSNAME ="" DATATYPE ="varchar" DESCRIPTION ="" FIELDNUMBER ="12" KEYTYPE ="NOT A KEY" NAME ="Size_Description" NULLABLE ="NULL" PICTURETEXT ="" PRECISION ="35" SCALE ="0"/>
        <TARGETFIELD BUSINESSNAME ="" DATATYPE ="varchar" DESCRIPTION ="" FIELDNUMBER ="13" KEYTYPE ="NOT A KEY" NAME ="Legacy_Size" NULLABLE ="NULL" PICTURETEXT ="" PRECISION ="30" SCALE ="0"/>
        <TARGETFIELD BUSINESSNAME ="" DATATYPE ="varchar" DESCRIPTION ="" FIELDNUMBER ="14" KEYTYPE ="NOT A KEY" NAME ="Cup_Code" NULLABLE ="NULL" PICTURETEXT ="" PRECISION ="30" SCALE ="0"/>
        <TARGETFIELD BUSINESSNAME ="" DATATYPE ="varchar" DESCRIPTION ="" FIELDNUMBER ="15" KEYTYPE ="NOT A KEY" NAME ="EAN" NULLABLE ="NULL" PICTURETEXT ="" PRECISION ="18" SCALE ="0"/>
        <TARGETFIELD BUSINESSNAME ="" DATATYPE ="varchar" DESCRIPTION ="" FIELDNUMBER ="16" KEYTYPE ="NOT A KEY" NAME ="Attribution_Code" NULLABLE ="NULL" PICTURETEXT ="" PRECISION ="6" SCALE ="0"/>
        <TARGETFIELD BUSINESSNAME ="" DATATYPE ="varchar" DESCRIPTION ="" FIELDNUMBER ="17" KEYTYPE ="NOT A KEY" NAME ="PutUp_Code" NULLABLE ="NULL" PICTURETEXT ="" PRECISION ="3" SCALE ="0"/>
        <TARGETFIELD BUSINESSNAME ="" DATATYPE ="decimal" DESCRIPTION ="" FIELDNUMBER ="18" KEYTYPE ="NOT A KEY" NAME ="retail_price" NULLABLE ="NULL" PICTURETEXT ="" PRECISION ="11" SCALE ="2"/>
        <TARGETFIELD BUSINESSNAME ="" DATATYPE ="varchar" DESCRIPTION ="" FIELDNUMBER ="19" KEYTYPE ="NOT A KEY" NAME ="multi_price" NULLABLE ="NULL" PICTURETEXT ="" PRECISION ="20" SCALE ="0"/>
        <TARGETFIELD BUSINESSNAME ="" DATATYPE ="varchar" DESCRIPTION ="" FIELDNUMBER ="20" KEYTYPE ="NOT A KEY" NAME ="currency" NULLABLE ="NULL" PICTURETEXT ="" PRECISION ="5" SCALE ="0"/>
        <TARGETFIELD BUSINESSNAME ="" DATATYPE ="varchar" DESCRIPTION ="" FIELDNUMBER ="21" KEYTYPE ="NOT A KEY" NAME ="price_eff_date" NULLABLE ="NULL" PICTURETEXT ="" PRECISION ="10" SCALE ="0"/>
        <TARGETFIELD BUSINESSNAME ="" DATATYPE ="varchar" DESCRIPTION ="" FIELDNUMBER ="22" KEYTYPE ="NOT A KEY" NAME ="department" NULLABLE ="NULL" PICTURETEXT ="" PRECISION ="10" SCALE ="0"/>
        <TARGETFIELD BUSINESSNAME ="" DATATYPE ="varchar" DESCRIPTION ="" FIELDNUMBER ="23" KEYTYPE ="NOT A KEY" NAME ="Cust_Mat_Nbr" NULLABLE ="NULL" PICTURETEXT ="" PRECISION ="35" SCALE ="0"/>
        <TARGETFIELD BUSINESSNAME ="" DATATYPE ="varchar" DESCRIPTION ="" FIELDNUMBER ="24" KEYTYPE ="NOT A KEY" NAME ="cust_nbr" NULLABLE ="NULL" PICTURETEXT ="" PRECISION ="10" SCALE ="0"/>
        <TARGETFIELD BUSINESSNAME ="" DATATYPE ="varchar" DESCRIPTION ="" FIELDNUMBER ="25" KEYTYPE ="NOT A KEY" NAME ="cust_name" NULLABLE ="NULL" PICTURETEXT ="" PRECISION ="35" SCALE ="0"/>
        <TARGETFIELD BUSINESSNAME ="" DATATYPE ="varchar" DESCRIPTION ="" FIELDNUMBER ="26" KEYTYPE ="NOT A KEY" NAME ="SAP_material" NULLABLE ="NULL" PICTURETEXT ="" PRECISION ="18" SCALE ="0"/>
        <TARGETFIELD BUSINESSNAME ="" DATATYPE ="varchar" DESCRIPTION ="" FIELDNUMBER ="27" KEYTYPE ="NOT A KEY" NAME ="SAP_grid" NULLABLE ="NULL" PICTURETEXT ="" PRECISION ="8" SCALE ="0"/>
        <TARGETFIELD BUSINESSNAME ="" DATATYPE ="varchar" DESCRIPTION ="" FIELDNUMBER ="28" KEYTYPE ="NOT A KEY" NAME ="Created_timestamp" NULLABLE ="NULL" PICTURETEXT ="" PRECISION ="26" SCALE ="0"/>
    </TARGET>
    <MAPPING DESCRIPTION ="This mapping is used to load data from flat file Teklynx.dat into Teklynx_SAP_data table" ISVALID ="YES" NAME ="m_TEKLYNX_SAP_DATA_LOAD" OBJECTVERSION ="1" VERSIONNUMBER ="1">
        <TRANSFORMATION DESCRIPTION ="This expression is used to trim the columns" NAME ="EXP_TRIM" OBJECTVERSION ="1" REUSABLE ="NO" TYPE ="Expression" VERSIONNUMBER ="1">
            <TRANSFORMFIELD DATATYPE ="string" DEFAULTVALUE ="" DESCRIPTION ="" NAME ="I_Key" PICTURETEXT ="" PORTTYPE ="INPUT" PRECISION ="40" SCALE ="0"/>
            <TRANSFORMFIELD DATATYPE ="string" DEFAULTVALUE ="" DESCRIPTION ="" NAME ="I_division" PICTURETEXT ="" PORTTYPE ="INPUT" PRECISION ="2" SCALE ="0"/>
            <TRANSFORMFIELD DATATYPE ="string" DEFAULTVALUE ="" DESCRIPTION ="" NAME ="I_product_line" PICTURETEXT ="" PORTTYPE ="INPUT" PRECISION ="4" SCALE ="0"/>
            <TRANSFORMFIELD DATATYPE ="string" DEFAULTVALUE ="" DESCRIPTION ="" NAME ="I_product_name" PICTURETEXT ="" PORTTYPE ="INPUT" PRECISION ="20" SCALE ="0"/>
            <TRANSFORMFIELD DATATYPE ="string" DEFAULTVALUE ="" DESCRIPTION ="" NAME ="I_style" PICTURETEXT ="" PORTTYPE ="INPUT" PRECISION ="8" SCALE ="0"/>
            <TRANSFORMFIELD DATATYPE ="string" DEFAULTVALUE ="" DESCRIPTION ="" NAME ="I_style_desc" PICTURETEXT ="" PORTTYPE ="INPUT" PRECISION ="35" SCALE ="0"/>
            <TRANSFORMFIELD DATATYPE ="string" DEFAULTVALUE ="" DESCRIPTION ="" NAME ="I_alt_style" PICTURETEXT ="" PORTTYPE ="INPUT" PRECISION ="30" SCALE ="0"/>
            <TRANSFORMFIELD DATATYPE ="string" DEFAULTVALUE ="" DESCRIPTION ="" NAME ="I_color" PICTURETEXT ="" PORTTYPE ="INPUT" PRECISION ="4" SCALE ="0"/>
            <TRANSFORMFIELD DATATYPE ="string" DEFAULTVALUE ="" DESCRIPTION ="" NAME ="I_color_desc" PICTURETEXT ="" PORTTYPE ="INPUT" PRECISION ="35" SCALE ="0"/>
            <TRANSFORMFIELD DATATYPE ="string" DEFAULTVALUE ="" DESCRIPTION ="" NAME ="I_alt_color" PICTURETEXT ="" PORTTYPE ="INPUT" PRECISION ="30" SCALE ="0"/>
            <TRANSFORMFIELD DATATYPE ="string" DEFAULTVALUE ="" DESCRIPTION ="" NAME ="I_size_cd" PICTURETEXT ="" PORTTYPE ="INPUT" PRECISION ="5" SCALE ="0"/>
            <TRANSFORMFIELD DATATYPE ="string" DEFAULTVALUE ="" DESCRIPTION ="" NAME ="I_size_desc" PICTURETEXT ="" PORTTYPE ="INPUT" PRECISION ="35" SCALE ="0"/>
            <TRANSFORMFIELD DATATYPE ="string" DEFAULTVALUE ="" DESCRIPTION ="" NAME ="I_alt_size1_cd" PICTURETEXT ="" PORTTYPE ="INPUT" PRECISION ="30" SCALE ="0"/>
            <TRANSFORMFIELD DATATYPE ="string" DEFAULTVALUE ="" DESCRIPTION ="" NAME ="I_cup" PICTURETEXT ="" PORTTYPE ="INPUT" PRECISION ="30" SCALE ="0"/>
            <TRANSFORMFIELD DATATYPE ="string" DEFAULTVALUE ="" DESCRIPTION ="" NAME ="I_upc_cd" PICTURETEXT ="" PORTTYPE ="INPUT" PRECISION ="18" SCALE ="0"/>
            <TRANSFORMFIELD DATATYPE ="string" DEFAULTVALUE ="" DESCRIPTION ="" NAME ="I_attribute_cd" PICTURETEXT ="" PORTTYPE ="INPUT" PRECISION ="6" SCALE ="0"/>
            <TRANSFORMFIELD DATATYPE ="string" DEFAULTVALUE ="" DESCRIPTION ="" NAME ="I_putup" PICTURETEXT ="" PORTTYPE ="INPUT" PRECISION ="3" SCALE ="0"/>
            <TRANSFORMFIELD DATATYPE ="string" DEFAULTVALUE ="" DESCRIPTION ="" NAME ="I_retail_price" PICTURETEXT ="" PORTTYPE ="INPUT" PRECISION ="11" SCALE ="0"/>
            <TRANSFORMFIELD DATATYPE ="string" DEFAULTVALUE ="" DESCRIPTION ="" NAME ="I_multiple_price" PICTURETEXT ="" PORTTYPE ="INPUT" PRECISION ="20" SCALE ="0"/>
            <TRANSFORMFIELD DATATYPE ="string" DEFAULTVALUE ="" DESCRIPTION ="" NAME ="I_currency" PICTURETEXT ="" PORTTYPE ="INPUT" PRECISION ="5" SCALE ="0"/>
            <TRANSFORMFIELD DATATYPE ="string" DEFAULTVALUE ="" DESCRIPTION ="" NAME ="I_price_eff_dt" PICTURETEXT ="" PORTTYPE ="INPUT" PRECISION ="8" SCALE ="0"/>
            <TRANSFORMFIELD DATATYPE ="string" DEFAULTVALUE ="" DESCRIPTION ="" NAME ="I_dept" PICTURETEXT ="" PORTTYPE ="INPUT" PRECISION ="10" SCALE ="0"/>
            <TRANSFORMFIELD DATATYPE ="string" DEFAULTVALUE ="" DESCRIPTION ="" NAME ="I_cust_sku" PICTURETEXT ="" PORTTYPE ="INPUT" PRECISION ="35" SCALE ="0"/>
            <TRANSFORMFIELD DATATYPE ="string" DEFAULTVALUE ="" DESCRIPTION ="" NAME ="I_cust_nbr" PICTURETEXT ="" PORTTYPE ="INPUT" PRECISION ="10" SCALE ="0"/>
            <TRANSFORMFIELD DATATYPE ="string" DEFAULTVALUE ="" DESCRIPTION ="" NAME ="I_cust_name" PICTURETEXT ="" PORTTYPE ="INPUT" PRECISION ="35" SCALE ="0"/>
            <TRANSFORMFIELD DATATYPE ="string" DEFAULTVALUE ="" DESCRIPTION ="" NAME ="I_material" PICTURETEXT ="" PORTTYPE ="INPUT" PRECISION ="18" SCALE ="0"/>
            <TRANSFORMFIELD DATATYPE ="string" DEFAULTVALUE ="" DESCRIPTION ="" NAME ="I_grid" PICTURETEXT ="" PORTTYPE ="INPUT" PRECISION ="8" SCALE ="0"/>
            <TRANSFORMFIELD DATATYPE ="string" DEFAULTVALUE ="" DESCRIPTION ="" NAME ="I_timestamp" PICTURETEXT ="" PORTTYPE ="INPUT" PRECISION ="15" SCALE ="0"/>
            <TRANSFORMFIELD DATATYPE ="string" DEFAULTVALUE ="ERROR(&apos;transformation error&apos;)" DESCRIPTION ="" EXPRESSION ="LTRIM(RTRIM(I_Key))" EXPRESSIONTYPE ="GENERAL" NAME ="O_key" PICTURETEXT ="" PORTTYPE ="OUTPUT" PRECISION ="40" SCALE ="0"/>
            <TRANSFORMFIELD DATATYPE ="string" DEFAULTVALUE ="ERROR(&apos;transformation error&apos;)" DESCRIPTION ="" EXPRESSION ="LTRIM(RTRIM(I_division))" EXPRESSIONTYPE ="GENERAL" NAME ="O_division" PICTURETEXT ="" PORTTYPE ="OUTPUT" PRECISION ="2" SCALE ="0"/>
            <TRANSFORMFIELD DATATYPE ="string" DEFAULTVALUE ="ERROR(&apos;transformation error&apos;)" DESCRIPTION ="" EXPRESSION ="ltrim(rtrim(I_product_line))" EXPRESSIONTYPE ="GENERAL" NAME ="O_product_line" PICTURETEXT ="" PORTTYPE ="OUTPUT" PRECISION ="4" SCALE ="0"/>
            <TRANSFORMFIELD DATATYPE ="string" DEFAULTVALUE ="ERROR(&apos;transformation error&apos;)" DESCRIPTION ="" EXPRESSION ="LTRIM(RTRIM(I_product_name))" EXPRESSIONTYPE ="GENERAL" NAME ="O_product_name" PICTURETEXT ="" PORTTYPE ="OUTPUT" PRECISION ="20" SCALE ="0"/>
            <TRANSFORMFIELD DATATYPE ="string" DEFAULTVALUE ="ERROR(&apos;transformation error&apos;)" DESCRIPTION ="" EXPRESSION ="LTRIM(RTRIM(I_style))" EXPRESSIONTYPE ="GENERAL" NAME ="O_style" PICTURETEXT ="" PORTTYPE ="OUTPUT" PRECISION ="8" SCALE ="0"/>
            <TRANSFORMFIELD DATATYPE ="string" DEFAULTVALUE ="ERROR(&apos;transformation error&apos;)" DESCRIPTION ="" EXPRESSION ="LTRIM(RTRIM(I_style_desc))" EXPRESSIONTYPE ="GENERAL" NAME ="O_style_desc" PICTURETEXT ="" PORTTYPE ="OUTPUT" PRECISION ="35" SCALE ="0"/>
            <TRANSFORMFIELD DATATYPE ="string" DEFAULTVALUE ="ERROR(&apos;transformation error&apos;)" DESCRIPTION ="" EXPRESSION ="LTRIM(RTRIM(I_alt_style))" EXPRESSIONTYPE ="GENERAL" NAME ="O_alt_style" PICTURETEXT ="" PORTTYPE ="OUTPUT" PRECISION ="30" SCALE ="0"/>
            <TRANSFORMFIELD DATATYPE ="string" DEFAULTVALUE ="ERROR(&apos;transformation error&apos;)" DESCRIPTION ="" EXPRESSION ="LTRIM(RTRIM(I_color))" EXPRESSIONTYPE ="GENERAL" NAME ="O_color" PICTURETEXT ="" PORTTYPE ="OUTPUT" PRECISION ="4" SCALE ="0"/>
            <TRANSFORMFIELD DATATYPE ="string" DEFAULTVALUE ="ERROR(&apos;transformation error&apos;)" DESCRIPTION ="" EXPRESSION ="LTRIM(RTRIM(I_color_desc))" EXPRESSIONTYPE ="GENERAL" NAME ="O_color_desc" PICTURETEXT ="" PORTTYPE ="OUTPUT" PRECISION ="35" SCALE ="0"/>
            <TRANSFORMFIELD DATATYPE ="string" DEFAULTVALUE ="ERROR(&apos;transformation error&apos;)" DESCRIPTION ="" EXPRESSION ="LTRIM(RTRIM(I_alt_color))" EXPRESSIONTYPE ="GENERAL" NAME ="O_alt_color" PICTURETEXT ="" PORTTYPE ="OUTPUT" PRECISION ="30" SCALE ="0"/>
            <TRANSFORMFIELD DATATYPE ="string" DEFAULTVALUE ="ERROR(&apos;transformation error&apos;)" DESCRIPTION ="" EXPRESSION ="LTRIM(RTRIM(I_size_cd))" EXPRESSIONTYPE ="GENERAL" NAME ="O_size_cd" PICTURETEXT ="" PORTTYPE ="OUTPUT" PRECISION ="5" SCALE ="0"/>
            <TRANSFORMFIELD DATATYPE ="string" DEFAULTVALUE ="ERROR(&apos;transformation error&apos;)" DESCRIPTION ="" EXPRESSION ="LTRIM(RTRIM(I_size_desc))" EXPRESSIONTYPE ="GENERAL" NAME ="O_size_desc" PICTURETEXT ="" PORTTYPE ="OUTPUT" PRECISION ="35" SCALE ="0"/>
            <TRANSFORMFIELD DATATYPE ="string" DEFAULTVALUE ="ERROR(&apos;transformation error&apos;)" DESCRIPTION ="" EXPRESSION ="LTRIM(RTRIM(I_alt_size1_cd))" EXPRESSIONTYPE ="GENERAL" NAME ="O_alt_size1_cd" PICTURETEXT ="" PORTTYPE ="OUTPUT" PRECISION ="30" SCALE ="0"/>
            <TRANSFORMFIELD DATATYPE ="string" DEFAULTVALUE ="ERROR(&apos;transformation error&apos;)" DESCRIPTION ="" EXPRESSION ="LTRIM(RTRIM(I_cup))" EXPRESSIONTYPE ="GENERAL" NAME ="O_cup" PICTURETEXT ="" PORTTYPE ="OUTPUT" PRECISION ="30" SCALE ="0"/>
            <TRANSFORMFIELD DATATYPE ="string" DEFAULTVALUE ="ERROR(&apos;transformation error&apos;)" DESCRIPTION ="" EXPRESSION ="LTRIM(RTRIM(I_upc_cd))" EXPRESSIONTYPE ="GENERAL" NAME ="O_upc_cd" PICTURETEXT ="" PORTTYPE ="OUTPUT" PRECISION ="18" SCALE ="0"/>
            <TRANSFORMFIELD DATATYPE ="string" DEFAULTVALUE ="ERROR(&apos;transformation error&apos;)" DESCRIPTION ="" EXPRESSION ="LTRIM(RTRIM(I_attribute_cd))" EXPRESSIONTYPE ="GENERAL" NAME ="O_attribution_code" PICTURETEXT ="" PORTTYPE ="OUTPUT" PRECISION ="6" SCALE ="0"/>
            <TRANSFORMFIELD DATATYPE ="string" DEFAULTVALUE ="ERROR(&apos;transformation error&apos;)" DESCRIPTION ="" EXPRESSION ="LTRIM(RTRIM(I_putup))" EXPRESSIONTYPE ="GENERAL" NAME ="O_putup_code" PICTURETEXT ="" PORTTYPE ="OUTPUT" PRECISION ="3" SCALE ="0"/>
            <TRANSFORMFIELD DATATYPE ="decimal" DEFAULTVALUE ="" DESCRIPTION ="" EXPRESSION ="to_decimal(LTRIM(RTRIM(I_retail_price))) / 100" EXPRESSIONTYPE ="GENERAL" NAME ="O_retail_price" PICTURETEXT ="" PORTTYPE ="OUTPUT" PRECISION ="11" SCALE ="2"/>
            <TRANSFORMFIELD DATATYPE ="string" DEFAULTVALUE ="" DESCRIPTION ="" EXPRESSION ="LTRIM(RTRIM(I_multiple_price))" EXPRESSIONTYPE ="GENERAL" NAME ="O_multiple_price" PICTURETEXT ="" PORTTYPE ="OUTPUT" PRECISION ="20" SCALE ="0"/>
            <TRANSFORMFIELD DATATYPE ="string" DEFAULTVALUE ="" DESCRIPTION ="" EXPRESSION ="LTRIM(RTRIM(I_currency))" EXPRESSIONTYPE ="GENERAL" NAME ="O_currency" PICTURETEXT ="" PORTTYPE ="OUTPUT" PRECISION ="5" SCALE ="0"/>
            <TRANSFORMFIELD DATATYPE ="string" DEFAULTVALUE ="" DESCRIPTION ="" EXPRESSION ="IIF(IS_DATE(LTRIM(RTRIM(I_price_eff_dt)),&apos;YYYYMMDD&apos;),&#xD;&#xA;To_CHAR(to_date(LTRIM(RTRIM(I_price_eff_dt)),&apos;YYYYMMDD&apos;),&apos;YYYY-MM-DD&apos;) ,  NULL)&#xD;&#xA;" EXPRESSIONTYPE ="GENERAL" NAME ="O_price_eff_date" PICTURETEXT ="" PORTTYPE ="OUTPUT" PRECISION ="10" SCALE ="0"/>
            <TRANSFORMFIELD DATATYPE ="string" DEFAULTVALUE ="ERROR(&apos;transformation error&apos;)" DESCRIPTION ="" EXPRESSION ="LTRIM(RTRIM(I_dept))" EXPRESSIONTYPE ="GENERAL" NAME ="O_department" PICTURETEXT ="" PORTTYPE ="OUTPUT" PRECISION ="10" SCALE ="0"/>
            <TRANSFORMFIELD DATATYPE ="string" DEFAULTVALUE ="ERROR(&apos;transformation error&apos;)" DESCRIPTION ="" EXPRESSION ="LTRIM(RTRIM(I_cust_sku))" EXPRESSIONTYPE ="GENERAL" NAME ="O_cust_mat_Nbr" PICTURETEXT ="" PORTTYPE ="OUTPUT" PRECISION ="35" SCALE ="0"/>
            <TRANSFORMFIELD DATATYPE ="string" DEFAULTVALUE ="ERROR(&apos;transformation error&apos;)" DESCRIPTION ="" EXPRESSION ="LTRIM(RTRIM(I_cust_nbr))" EXPRESSIONTYPE ="GENERAL" NAME ="O_cust_nbr" PICTURETEXT ="" PORTTYPE ="OUTPUT" PRECISION ="10" SCALE ="0"/>
            <TRANSFORMFIELD DATATYPE ="string" DEFAULTVALUE ="ERROR(&apos;transformation error&apos;)" DESCRIPTION ="" EXPRESSION ="LTRIM(RTRIM(I_cust_name))" EXPRESSIONTYPE ="GENERAL" NAME ="O_cust_name" PICTURETEXT ="" PORTTYPE ="OUTPUT" PRECISION ="35" SCALE ="0"/>
            <TRANSFORMFIELD DATATYPE ="string" DEFAULTVALUE ="ERROR(&apos;transformation error&apos;)" DESCRIPTION ="" EXPRESSION ="LTRIM(RTRIM(I_material))" EXPRESSIONTYPE ="GENERAL" NAME ="O_SAP_material" PICTURETEXT ="" PORTTYPE ="OUTPUT" PRECISION ="18" SCALE ="0"/>
            <TRANSFORMFIELD DATATYPE ="string" DEFAULTVALUE ="ERROR(&apos;transformation error&apos;)" DESCRIPTION ="" EXPRESSION ="LTRIM(RTRIM(I_grid))" EXPRESSIONTYPE ="GENERAL" NAME ="O_SAP_grid" PICTURETEXT ="" PORTTYPE ="OUTPUT" PRECISION ="8" SCALE ="0"/>
            <TRANSFORMFIELD DATATYPE ="string" DEFAULTVALUE ="" DESCRIPTION ="" EXPRESSION ="to_CHAR(to_DATE(LTRIM(RTRIM(I_timestamp)),&apos;YYYYMMDDHH24MISS&apos;),&apos;MM/DD/YYYY HH24:MI:SS&apos;)" EXPRESSIONTYPE ="GENERAL" NAME ="O_created_timestamp" PICTURETEXT ="" PORTTYPE ="OUTPUT" PRECISION ="26" SCALE ="0"/>
            <TABLEATTRIBUTE NAME ="Tracing Level" VALUE ="Normal"/>
        </TRANSFORMATION>
        <TRANSFORMATION DESCRIPTION ="Source definition of flat file" NAME ="SQ_FF_TEKLYNX" OBJECTVERSION ="1" REUSABLE ="NO" TYPE ="Source Qualifier" VERSIONNUMBER ="1">
            <TRANSFORMFIELD DATATYPE ="string" DEFAULTVALUE ="" DESCRIPTION ="" NAME ="Key" PICTURETEXT ="" PORTTYPE ="INPUT/OUTPUT" PRECISION ="40" SCALE ="0"/>
            <TRANSFORMFIELD DATATYPE ="string" DEFAULTVALUE ="" DESCRIPTION ="" NAME ="division" PICTURETEXT ="" PORTTYPE ="INPUT/OUTPUT" PRECISION ="2" SCALE ="0"/>
            <TRANSFORMFIELD DATATYPE ="string" DEFAULTVALUE ="" DESCRIPTION ="" NAME ="product_line" PICTURETEXT ="" PORTTYPE ="INPUT/OUTPUT" PRECISION ="4" SCALE ="0"/>
            <TRANSFORMFIELD DATATYPE ="string" DEFAULTVALUE ="" DESCRIPTION ="" NAME ="product_name" PICTURETEXT ="" PORTTYPE ="INPUT/OUTPUT" PRECISION ="20" SCALE ="0"/>
            <TRANSFORMFIELD DATATYPE ="string" DEFAULTVALUE ="" DESCRIPTION ="" NAME ="style" PICTURETEXT ="" PORTTYPE ="INPUT/OUTPUT" PRECISION ="8" SCALE ="0"/>
            <TRANSFORMFIELD DATATYPE ="string" DEFAULTVALUE ="" DESCRIPTION ="" NAME ="style_desc" PICTURETEXT ="" PORTTYPE ="INPUT/OUTPUT" PRECISION ="35" SCALE ="0"/>
            <TRANSFORMFIELD DATATYPE ="string" DEFAULTVALUE ="" DESCRIPTION ="" NAME ="alt_style" PICTURETEXT ="" PORTTYPE ="INPUT/OUTPUT" PRECISION ="30" SCALE ="0"/>
            <TRANSFORMFIELD DATATYPE ="string" DEFAULTVALUE ="" DESCRIPTION ="" NAME ="color" PICTURETEXT ="" PORTTYPE ="INPUT/OUTPUT" PRECISION ="4" SCALE ="0"/>
            <TRANSFORMFIELD DATATYPE ="string" DEFAULTVALUE ="" DESCRIPTION ="" NAME ="color_desc" PICTURETEXT ="" PORTTYPE ="INPUT/OUTPUT" PRECISION ="35" SCALE ="0"/>
            <TRANSFORMFIELD DATATYPE ="string" DEFAULTVALUE ="" DESCRIPTION ="" NAME ="alt_color" PICTURETEXT ="" PORTTYPE ="INPUT/OUTPUT" PRECISION ="30" SCALE ="0"/>
            <TRANSFORMFIELD DATATYPE ="string" DEFAULTVALUE ="" DESCRIPTION ="" NAME ="size_cd" PICTURETEXT ="" PORTTYPE ="INPUT/OUTPUT" PRECISION ="5" SCALE ="0"/>
            <TRANSFORMFIELD DATATYPE ="string" DEFAULTVALUE ="" DESCRIPTION ="" NAME ="size_desc" PICTURETEXT ="" PORTTYPE ="INPUT/OUTPUT" PRECISION ="35" SCALE ="0"/>
            <TRANSFORMFIELD DATATYPE ="string" DEFAULTVALUE ="" DESCRIPTION ="" NAME ="alt_size1_cd" PICTURETEXT ="" PORTTYPE ="INPUT/OUTPUT" PRECISION ="30" SCALE ="0"/>
            <TRANSFORMFIELD DATATYPE ="string" DEFAULTVALUE ="" DESCRIPTION ="" NAME ="cup" PICTURETEXT ="" PORTTYPE ="INPUT/OUTPUT" PRECISION ="30" SCALE ="0"/>
            <TRANSFORMFIELD DATATYPE ="string" DEFAULTVALUE ="" DESCRIPTION ="" NAME ="upc_cd" PICTURETEXT ="" PORTTYPE ="INPUT/OUTPUT" PRECISION ="18" SCALE ="0"/>
            <TRANSFORMFIELD DATATYPE ="string" DEFAULTVALUE ="" DESCRIPTION ="" NAME ="attribute_cd" PICTURETEXT ="" PORTTYPE ="INPUT/OUTPUT" PRECISION ="6" SCALE ="0"/>
            <TRANSFORMFIELD DATATYPE ="string" DEFAULTVALUE ="" DESCRIPTION ="" NAME ="putup" PICTURETEXT ="" PORTTYPE ="INPUT/OUTPUT" PRECISION ="3" SCALE ="0"/>
            <TRANSFORMFIELD DATATYPE ="string" DEFAULTVALUE ="" DESCRIPTION ="" NAME ="retail_price" PICTURETEXT ="" PORTTYPE ="INPUT/OUTPUT" PRECISION ="11" SCALE ="0"/>
            <TRANSFORMFIELD DATATYPE ="string" DEFAULTVALUE ="" DESCRIPTION ="" NAME ="multiple_price" PICTURETEXT ="" PORTTYPE ="INPUT/OUTPUT" PRECISION ="20" SCALE ="0"/>
            <TRANSFORMFIELD DATATYPE ="string" DEFAULTVALUE ="" DESCRIPTION ="" NAME ="currency" PICTURETEXT ="" PORTTYPE ="INPUT/OUTPUT" PRECISION ="5" SCALE ="0"/>
            <TRANSFORMFIELD DATATYPE ="string" DEFAULTVALUE ="" DESCRIPTION ="" NAME ="price_eff_dt" PICTURETEXT ="" PORTTYPE ="INPUT/OUTPUT" PRECISION ="8" SCALE ="0"/>
            <TRANSFORMFIELD DATATYPE ="string" DEFAULTVALUE ="" DESCRIPTION ="" NAME ="dept" PICTURETEXT ="" PORTTYPE ="INPUT/OUTPUT" PRECISION ="10" SCALE ="0"/>
            <TRANSFORMFIELD DATATYPE ="string" DEFAULTVALUE ="" DESCRIPTION ="" NAME ="cust_sku" PICTURETEXT ="" PORTTYPE ="INPUT/OUTPUT" PRECISION ="35" SCALE ="0"/>
            <TRANSFORMFIELD DATATYPE ="string" DEFAULTVALUE ="" DESCRIPTION ="" NAME ="cust_nbr" PICTURETEXT ="" PORTTYPE ="INPUT/OUTPUT" PRECISION ="10" SCALE ="0"/>
            <TRANSFORMFIELD DATATYPE ="string" DEFAULTVALUE ="" DESCRIPTION ="" NAME ="cust_name" PICTURETEXT ="" PORTTYPE ="INPUT/OUTPUT" PRECISION ="35" SCALE ="0"/>
            <TRANSFORMFIELD DATATYPE ="string" DEFAULTVALUE ="" DESCRIPTION ="" NAME ="material" PICTURETEXT ="" PORTTYPE ="INPUT/OUTPUT" PRECISION ="18" SCALE ="0"/>
            <TRANSFORMFIELD DATATYPE ="string" DEFAULTVALUE ="" DESCRIPTION ="" NAME ="grid" PICTURETEXT ="" PORTTYPE ="INPUT/OUTPUT" PRECISION ="8" SCALE ="0"/>
            <TRANSFORMFIELD DATATYPE ="string" DEFAULTVALUE ="" DESCRIPTION ="" NAME ="timestamp" PICTURETEXT ="" PORTTYPE ="INPUT/OUTPUT" PRECISION ="15" SCALE ="0"/>
            <TABLEATTRIBUTE NAME ="Sql Query" VALUE =""/>
            <TABLEATTRIBUTE NAME ="User Defined Join" VALUE =""/>
            <TABLEATTRIBUTE NAME ="Source Filter" VALUE =""/>
            <TABLEATTRIBUTE NAME ="Number Of Sorted Ports" VALUE ="0"/>
            <TABLEATTRIBUTE NAME ="Tracing Level" VALUE ="Normal"/>
            <TABLEATTRIBUTE NAME ="Select Distinct" VALUE ="NO"/>
            <TABLEATTRIBUTE NAME ="Is Partitionable" VALUE ="NO"/>
            <TABLEATTRIBUTE NAME ="Pre SQL" VALUE =""/>
            <TABLEATTRIBUTE NAME ="Post SQL" VALUE =""/>
            <TABLEATTRIBUTE NAME ="Output is deterministic" VALUE ="NO"/>
            <TABLEATTRIBUTE NAME ="Output is repeatable" VALUE ="Never"/>
        </TRANSFORMATION>
        <INSTANCE DESCRIPTION ="Target definition" NAME ="Teklynx_SAP_data" TRANSFORMATION_NAME ="Teklynx_SAP_data" TRANSFORMATION_TYPE ="Target Definition" TYPE ="TARGET"/>
        <INSTANCE DBDNAME ="Flat_File" DESCRIPTION ="Source Definition" NAME ="FF_TEKLYNX" TRANSFORMATION_NAME ="FF_TEKLYNX" TRANSFORMATION_TYPE ="Source Definition" TYPE ="SOURCE"/>
        <INSTANCE DESCRIPTION ="This expression is used to trim the columns" NAME ="EXP_TRIM" REUSABLE ="NO" TRANSFORMATION_NAME ="EXP_TRIM" TRANSFORMATION_TYPE ="Expression" TYPE ="TRANSFORMATION"/>
        <INSTANCE DESCRIPTION ="Source definition of flat file" NAME ="SQ_FF_TEKLYNX" REUSABLE ="NO" TRANSFORMATION_NAME ="SQ_FF_TEKLYNX" TRANSFORMATION_TYPE ="Source Qualifier" TYPE ="TRANSFORMATION">
            <ASSOCIATED_SOURCE_INSTANCE NAME ="FF_TEKLYNX"/>
        </INSTANCE>
        <CONNECTOR FROMFIELD ="O_retail_price" FROMINSTANCE ="EXP_TRIM" FROMINSTANCETYPE ="Expression" TOFIELD ="retail_price" TOINSTANCE ="Teklynx_SAP_data" TOINSTANCETYPE ="Target Definition"/>
        <CONNECTOR FROMFIELD ="O_multiple_price" FROMINSTANCE ="EXP_TRIM" FROMINSTANCETYPE ="Expression" TOFIELD ="multi_price" TOINSTANCE ="Teklynx_SAP_data" TOINSTANCETYPE ="Target Definition"/>
        <CONNECTOR FROMFIELD ="O_currency" FROMINSTANCE ="EXP_TRIM" FROMINSTANCETYPE ="Expression" TOFIELD ="currency" TOINSTANCE ="Teklynx_SAP_data" TOINSTANCETYPE ="Target Definition"/>
        <CONNECTOR FROMFIELD ="O_price_eff_date" FROMINSTANCE ="EXP_TRIM" FROMINSTANCETYPE ="Expression" TOFIELD ="price_eff_date" TOINSTANCE ="Teklynx_SAP_data" TOINSTANCETYPE ="Target Definition"/>
        <CONNECTOR FROMFIELD ="O_created_timestamp" FROMINSTANCE ="EXP_TRIM" FROMINSTANCETYPE ="Expression" TOFIELD ="Created_timestamp" TOINSTANCE ="Teklynx_SAP_data" TOINSTANCETYPE ="Target Definition"/>
        <CONNECTOR FROMFIELD ="O_key" FROMINSTANCE ="EXP_TRIM" FROMINSTANCETYPE ="Expression" TOFIELD ="Hbi_key" TOINSTANCE ="Teklynx_SAP_data" TOINSTANCETYPE ="Target Definition"/>
        <CONNECTOR FROMFIELD ="O_division" FROMINSTANCE ="EXP_TRIM" FROMINSTANCETYPE ="Expression" TOFIELD ="SAP_division" TOINSTANCE ="Teklynx_SAP_data" TOINSTANCETYPE ="Target Definition"/>
        <CONNECTOR FROMFIELD ="O_product_line" FROMINSTANCE ="EXP_TRIM" FROMINSTANCETYPE ="Expression" TOFIELD ="product_line" TOINSTANCE ="Teklynx_SAP_data" TOINSTANCETYPE ="Target Definition"/>
        <CONNECTOR FROMFIELD ="O_product_name" FROMINSTANCE ="EXP_TRIM" FROMINSTANCETYPE ="Expression" TOFIELD ="product_name" TOINSTANCE ="Teklynx_SAP_data" TOINSTANCETYPE ="Target Definition"/>
        <CONNECTOR FROMFIELD ="O_style" FROMINSTANCE ="EXP_TRIM" FROMINSTANCETYPE ="Expression" TOFIELD ="style" TOINSTANCE ="Teklynx_SAP_data" TOINSTANCETYPE ="Target Definition"/>
        <CONNECTOR FROMFIELD ="O_style_desc" FROMINSTANCE ="EXP_TRIM" FROMINSTANCETYPE ="Expression" TOFIELD ="Style_Description" TOINSTANCE ="Teklynx_SAP_data" TOINSTANCETYPE ="Target Definition"/>
        <CONNECTOR FROMFIELD ="O_alt_style" FROMINSTANCE ="EXP_TRIM" FROMINSTANCETYPE ="Expression" TOFIELD ="Legacy_Style" TOINSTANCE ="Teklynx_SAP_data" TOINSTANCETYPE ="Target Definition"/>
        <CONNECTOR FROMFIELD ="O_color" FROMINSTANCE ="EXP_TRIM" FROMINSTANCETYPE ="Expression" TOFIELD ="color" TOINSTANCE ="Teklynx_SAP_data" TOINSTANCETYPE ="Target Definition"/>
        <CONNECTOR FROMFIELD ="O_color_desc" FROMINSTANCE ="EXP_TRIM" FROMINSTANCETYPE ="Expression" TOFIELD ="color_description" TOINSTANCE ="Teklynx_SAP_data" TOINSTANCETYPE ="Target Definition"/>
        <CONNECTOR FROMFIELD ="O_alt_color" FROMINSTANCE ="EXP_TRIM" FROMINSTANCETYPE ="Expression" TOFIELD ="Legacy_Color" TOINSTANCE ="Teklynx_SAP_data" TOINSTANCETYPE ="Target Definition"/>
        <CONNECTOR FROMFIELD ="O_size_cd" FROMINSTANCE ="EXP_TRIM" FROMINSTANCETYPE ="Expression" TOFIELD ="size" TOINSTANCE ="Teklynx_SAP_data" TOINSTANCETYPE ="Target Definition"/>
        <CONNECTOR FROMFIELD ="O_size_desc" FROMINSTANCE ="EXP_TRIM" FROMINSTANCETYPE ="Expression" TOFIELD ="Size_Description" TOINSTANCE ="Teklynx_SAP_data" TOINSTANCETYPE ="Target Definition"/>
        <CONNECTOR FROMFIELD ="O_alt_size1_cd" FROMINSTANCE ="EXP_TRIM" FROMINSTANCETYPE ="Expression" TOFIELD ="Legacy_Size" TOINSTANCE ="Teklynx_SAP_data" TOINSTANCETYPE ="Target Definition"/>
        <CONNECTOR FROMFIELD ="O_cup" FROMINSTANCE ="EXP_TRIM" FROMINSTANCETYPE ="Expression" TOFIELD ="Cup_Code" TOINSTANCE ="Teklynx_SAP_data" TOINSTANCETYPE ="Target Definition"/>
        <CONNECTOR FROMFIELD ="O_upc_cd" FROMINSTANCE ="EXP_TRIM" FROMINSTANCETYPE ="Expression" TOFIELD ="EAN" TOINSTANCE ="Teklynx_SAP_data" TOINSTANCETYPE ="Target Definition"/>
        <CONNECTOR FROMFIELD ="O_attribution_code" FROMINSTANCE ="EXP_TRIM" FROMINSTANCETYPE ="Expression" TOFIELD ="Attribution_Code" TOINSTANCE ="Teklynx_SAP_data" TOINSTANCETYPE ="Target Definition"/>
        <CONNECTOR FROMFIELD ="O_putup_code" FROMINSTANCE ="EXP_TRIM" FROMINSTANCETYPE ="Expression" TOFIELD ="PutUp_Code" TOINSTANCE ="Teklynx_SAP_data" TOINSTANCETYPE ="Target Definition"/>
        <CONNECTOR FROMFIELD ="O_department" FROMINSTANCE ="EXP_TRIM" FROMINSTANCETYPE ="Expression" TOFIELD ="department" TOINSTANCE ="Teklynx_SAP_data" TOINSTANCETYPE ="Target Definition"/>
        <CONNECTOR FROMFIELD ="O_cust_mat_Nbr" FROMINSTANCE ="EXP_TRIM" FROMINSTANCETYPE ="Expression" TOFIELD ="Cust_Mat_Nbr" TOINSTANCE ="Teklynx_SAP_data" TOINSTANCETYPE ="Target Definition"/>
        <CONNECTOR FROMFIELD ="O_cust_nbr" FROMINSTANCE ="EXP_TRIM" FROMINSTANCETYPE ="Expression" TOFIELD ="cust_nbr" TOINSTANCE ="Teklynx_SAP_data" TOINSTANCETYPE ="Target Definition"/>
        <CONNECTOR FROMFIELD ="O_cust_name" FROMINSTANCE ="EXP_TRIM" FROMINSTANCETYPE ="Expression" TOFIELD ="cust_name" TOINSTANCE ="Teklynx_SAP_data" TOINSTANCETYPE ="Target Definition"/>
        <CONNECTOR FROMFIELD ="O_SAP_material" FROMINSTANCE ="EXP_TRIM" FROMINSTANCETYPE ="Expression" TOFIELD ="SAP_material" TOINSTANCE ="Teklynx_SAP_data" TOINSTANCETYPE ="Target Definition"/>
        <CONNECTOR FROMFIELD ="O_SAP_grid" FROMINSTANCE ="EXP_TRIM" FROMINSTANCETYPE ="Expression" TOFIELD ="SAP_grid" TOINSTANCE ="Teklynx_SAP_data" TOINSTANCETYPE ="Target Definition"/>
        <CONNECTOR FROMFIELD ="size_cd" FROMINSTANCE ="FF_TEKLYNX" FROMINSTANCETYPE ="Source Definition" TOFIELD ="size_cd" TOINSTANCE ="SQ_FF_TEKLYNX" TOINSTANCETYPE ="Source Qualifier"/>
        <CONNECTOR FROMFIELD ="size_desc" FROMINSTANCE ="FF_TEKLYNX" FROMINSTANCETYPE ="Source Definition" TOFIELD ="size_desc" TOINSTANCE ="SQ_FF_TEKLYNX" TOINSTANCETYPE ="Source Qualifier"/>
        <CONNECTOR FROMFIELD ="alt_size1_cd" FROMINSTANCE ="FF_TEKLYNX" FROMINSTANCETYPE ="Source Definition" TOFIELD ="alt_size1_cd" TOINSTANCE ="SQ_FF_TEKLYNX" TOINSTANCETYPE ="Source Qualifier"/>
        <CONNECTOR FROMFIELD ="cup" FROMINSTANCE ="FF_TEKLYNX" FROMINSTANCETYPE ="Source Definition" TOFIELD ="cup" TOINSTANCE ="SQ_FF_TEKLYNX" TOINSTANCETYPE ="Source Qualifier"/>
        <CONNECTOR FROMFIELD ="upc_cd" FROMINSTANCE ="FF_TEKLYNX" FROMINSTANCETYPE ="Source Definition" TOFIELD ="upc_cd" TOINSTANCE ="SQ_FF_TEKLYNX" TOINSTANCETYPE ="Source Qualifier"/>
        <CONNECTOR FROMFIELD ="attribute_cd" FROMINSTANCE ="FF_TEKLYNX" FROMINSTANCETYPE ="Source Definition" TOFIELD ="attribute_cd" TOINSTANCE ="SQ_FF_TEKLYNX" TOINSTANCETYPE ="Source Qualifier"/>
        <CONNECTOR FROMFIELD ="putup" FROMINSTANCE ="FF_TEKLYNX" FROMINSTANCETYPE ="Source Definition" TOFIELD ="putup" TOINSTANCE ="SQ_FF_TEKLYNX" TOINSTANCETYPE ="Source Qualifier"/>
        <CONNECTOR FROMFIELD ="retail_price" FROMINSTANCE ="FF_TEKLYNX" FROMINSTANCETYPE ="Source Definition" TOFIELD ="retail_price" TOINSTANCE ="SQ_FF_TEKLYNX" TOINSTANCETYPE ="Source Qualifier"/>
        <CONNECTOR FROMFIELD ="multiple_price" FROMINSTANCE ="FF_TEKLYNX" FROMINSTANCETYPE ="Source Definition" TOFIELD ="multiple_price" TOINSTANCE ="SQ_FF_TEKLYNX" TOINSTANCETYPE ="Source Qualifier"/>
        <CONNECTOR FROMFIELD ="currency" FROMINSTANCE ="FF_TEKLYNX" FROMINSTANCETYPE ="Source Definition" TOFIELD ="currency" TOINSTANCE ="SQ_FF_TEKLYNX" TOINSTANCETYPE ="Source Qualifier"/>
        <CONNECTOR FROMFIELD ="price_eff_dt" FROMINSTANCE ="FF_TEKLYNX" FROMINSTANCETYPE ="Source Definition" TOFIELD ="price_eff_dt" TOINSTANCE ="SQ_FF_TEKLYNX" TOINSTANCETYPE ="Source Qualifier"/>
        <CONNECTOR FROMFIELD ="dept" FROMINSTANCE ="FF_TEKLYNX" FROMINSTANCETYPE ="Source Definition" TOFIELD ="dept" TOINSTANCE ="SQ_FF_TEKLYNX" TOINSTANCETYPE ="Source Qualifier"/>
        <CONNECTOR FROMFIELD ="cust_sku" FROMINSTANCE ="FF_TEKLYNX" FROMINSTANCETYPE ="Source Definition" TOFIELD ="cust_sku" TOINSTANCE ="SQ_FF_TEKLYNX" TOINSTANCETYPE ="Source Qualifier"/>
        <CONNECTOR FROMFIELD ="cust_nbr" FROMINSTANCE ="FF_TEKLYNX" FROMINSTANCETYPE ="Source Definition" TOFIELD ="cust_nbr" TOINSTANCE ="SQ_FF_TEKLYNX" TOINSTANCETYPE ="Source Qualifier"/>
        <CONNECTOR FROMFIELD ="cust_name" FROMINSTANCE ="FF_TEKLYNX" FROMINSTANCETYPE ="Source Definition" TOFIELD ="cust_name" TOINSTANCE ="SQ_FF_TEKLYNX" TOINSTANCETYPE ="Source Qualifier"/>
        <CONNECTOR FROMFIELD ="material" FROMINSTANCE ="FF_TEKLYNX" FROMINSTANCETYPE ="Source Definition" TOFIELD ="material" TOINSTANCE ="SQ_FF_TEKLYNX" TOINSTANCETYPE ="Source Qualifier"/>
        <CONNECTOR FROMFIELD ="grid" FROMINSTANCE ="FF_TEKLYNX" FROMINSTANCETYPE ="Source Definition" TOFIELD ="grid" TOINSTANCE ="SQ_FF_TEKLYNX" TOINSTANCETYPE ="Source Qualifier"/>
        <CONNECTOR FROMFIELD ="timestamp" FROMINSTANCE ="FF_TEKLYNX" FROMINSTANCETYPE ="Source Definition" TOFIELD ="timestamp" TOINSTANCE ="SQ_FF_TEKLYNX" TOINSTANCETYPE ="Source Qualifier"/>
        <CONNECTOR FROMFIELD ="Key" FROMINSTANCE ="FF_TEKLYNX" FROMINSTANCETYPE ="Source Definition" TOFIELD ="Key" TOINSTANCE ="SQ_FF_TEKLYNX" TOINSTANCETYPE ="Source Qualifier"/>
        <CONNECTOR FROMFIELD ="division" FROMINSTANCE ="FF_TEKLYNX" FROMINSTANCETYPE ="Source Definition" TOFIELD ="division" TOINSTANCE ="SQ_FF_TEKLYNX" TOINSTANCETYPE ="Source Qualifier"/>
        <CONNECTOR FROMFIELD ="product_line" FROMINSTANCE ="FF_TEKLYNX" FROMINSTANCETYPE ="Source Definition" TOFIELD ="product_line" TOINSTANCE ="SQ_FF_TEKLYNX" TOINSTANCETYPE ="Source Qualifier"/>
        <CONNECTOR FROMFIELD ="product_name" FROMINSTANCE ="FF_TEKLYNX" FROMINSTANCETYPE ="Source Definition" TOFIELD ="product_name" TOINSTANCE ="SQ_FF_TEKLYNX" TOINSTANCETYPE ="Source Qualifier"/>
        <CONNECTOR FROMFIELD ="style" FROMINSTANCE ="FF_TEKLYNX" FROMINSTANCETYPE ="Source Definition" TOFIELD ="style" TOINSTANCE ="SQ_FF_TEKLYNX" TOINSTANCETYPE ="Source Qualifier"/>
        <CONNECTOR FROMFIELD ="style_desc" FROMINSTANCE ="FF_TEKLYNX" FROMINSTANCETYPE ="Source Definition" TOFIELD ="style_desc" TOINSTANCE ="SQ_FF_TEKLYNX" TOINSTANCETYPE ="Source Qualifier"/>
        <CONNECTOR FROMFIELD ="alt_style" FROMINSTANCE ="FF_TEKLYNX" FROMINSTANCETYPE ="Source Definition" TOFIELD ="alt_style" TOINSTANCE ="SQ_FF_TEKLYNX" TOINSTANCETYPE ="Source Qualifier"/>
        <CONNECTOR FROMFIELD ="color" FROMINSTANCE ="FF_TEKLYNX" FROMINSTANCETYPE ="Source Definition" TOFIELD ="color" TOINSTANCE ="SQ_FF_TEKLYNX" TOINSTANCETYPE ="Source Qualifier"/>
        <CONNECTOR FROMFIELD ="color_desc" FROMINSTANCE ="FF_TEKLYNX" FROMINSTANCETYPE ="Source Definition" TOFIELD ="color_desc" TOINSTANCE ="SQ_FF_TEKLYNX" TOINSTANCETYPE ="Source Qualifier"/>
        <CONNECTOR FROMFIELD ="alt_color" FROMINSTANCE ="FF_TEKLYNX" FROMINSTANCETYPE ="Source Definition" TOFIELD ="alt_color" TOINSTANCE ="SQ_FF_TEKLYNX" TOINSTANCETYPE ="Source Qualifier"/>
        <CONNECTOR FROMFIELD ="division" FROMINSTANCE ="SQ_FF_TEKLYNX" FROMINSTANCETYPE ="Source Qualifier" TOFIELD ="I_division" TOINSTANCE ="EXP_TRIM" TOINSTANCETYPE ="Expression"/>
        <CONNECTOR FROMFIELD ="product_line" FROMINSTANCE ="SQ_FF_TEKLYNX" FROMINSTANCETYPE ="Source Qualifier" TOFIELD ="I_product_line" TOINSTANCE ="EXP_TRIM" TOINSTANCETYPE ="Expression"/>
        <CONNECTOR FROMFIELD ="product_name" FROMINSTANCE ="SQ_FF_TEKLYNX" FROMINSTANCETYPE ="Source Qualifier" TOFIELD ="I_product_name" TOINSTANCE ="EXP_TRIM" TOINSTANCETYPE ="Expression"/>
        <CONNECTOR FROMFIELD ="style" FROMINSTANCE ="SQ_FF_TEKLYNX" FROMINSTANCETYPE ="Source Qualifier" TOFIELD ="I_style" TOINSTANCE ="EXP_TRIM" TOINSTANCETYPE ="Expression"/>
        <CONNECTOR FROMFIELD ="Key" FROMINSTANCE ="SQ_FF_TEKLYNX" FROMINSTANCETYPE ="Source Qualifier" TOFIELD ="I_Key" TOINSTANCE ="EXP_TRIM" TOINSTANCETYPE ="Expression"/>
        <CONNECTOR FROMFIELD ="style_desc" FROMINSTANCE ="SQ_FF_TEKLYNX" FROMINSTANCETYPE ="Source Qualifier" TOFIELD ="I_style_desc" TOINSTANCE ="EXP_TRIM" TOINSTANCETYPE ="Expression"/>
        <CONNECTOR FROMFIELD ="alt_style" FROMINSTANCE ="SQ_FF_TEKLYNX" FROMINSTANCETYPE ="Source Qualifier" TOFIELD ="I_alt_style" TOINSTANCE ="EXP_TRIM" TOINSTANCETYPE ="Expression"/>
        <CONNECTOR FROMFIELD ="color" FROMINSTANCE ="SQ_FF_TEKLYNX" FROMINSTANCETYPE ="Source Qualifier" TOFIELD ="I_color" TOINSTANCE ="EXP_TRIM" TOINSTANCETYPE ="Expression"/>
        <CONNECTOR FROMFIELD ="color_desc" FROMINSTANCE ="SQ_FF_TEKLYNX" FROMINSTANCETYPE ="Source Qualifier" TOFIELD ="I_color_desc" TOINSTANCE ="EXP_TRIM" TOINSTANCETYPE ="Expression"/>
        <CONNECTOR FROMFIELD ="alt_color" FROMINSTANCE ="SQ_FF_TEKLYNX" FROMINSTANCETYPE ="Source Qualifier" TOFIELD ="I_alt_color" TOINSTANCE ="EXP_TRIM" TOINSTANCETYPE ="Expression"/>
        <CONNECTOR FROMFIELD ="size_cd" FROMINSTANCE ="SQ_FF_TEKLYNX" FROMINSTANCETYPE ="Source Qualifier" TOFIELD ="I_size_cd" TOINSTANCE ="EXP_TRIM" TOINSTANCETYPE ="Expression"/>
        <CONNECTOR FROMFIELD ="size_desc" FROMINSTANCE ="SQ_FF_TEKLYNX" FROMINSTANCETYPE ="Source Qualifier" TOFIELD ="I_size_desc" TOINSTANCE ="EXP_TRIM" TOINSTANCETYPE ="Expression"/>
        <CONNECTOR FROMFIELD ="alt_size1_cd" FROMINSTANCE ="SQ_FF_TEKLYNX" FROMINSTANCETYPE ="Source Qualifier" TOFIELD ="I_alt_size1_cd" TOINSTANCE ="EXP_TRIM" TOINSTANCETYPE ="Expression"/>
        <CONNECTOR FROMFIELD ="cup" FROMINSTANCE ="SQ_FF_TEKLYNX" FROMINSTANCETYPE ="Source Qualifier" TOFIELD ="I_cup" TOINSTANCE ="EXP_TRIM" TOINSTANCETYPE ="Expression"/>
        <CONNECTOR FROMFIELD ="upc_cd" FROMINSTANCE ="SQ_FF_TEKLYNX" FROMINSTANCETYPE ="Source Qualifier" TOFIELD ="I_upc_cd" TOINSTANCE ="EXP_TRIM" TOINSTANCETYPE ="Expression"/>
        <CONNECTOR FROMFIELD ="attribute_cd" FROMINSTANCE ="SQ_FF_TEKLYNX" FROMINSTANCETYPE ="Source Qualifier" TOFIELD ="I_attribute_cd" TOINSTANCE ="EXP_TRIM" TOINSTANCETYPE ="Expression"/>
        <CONNECTOR FROMFIELD ="putup" FROMINSTANCE ="SQ_FF_TEKLYNX" FROMINSTANCETYPE ="Source Qualifier" TOFIELD ="I_putup" TOINSTANCE ="EXP_TRIM" TOINSTANCETYPE ="Expression"/>
        <CONNECTOR FROMFIELD ="retail_price" FROMINSTANCE ="SQ_FF_TEKLYNX" FROMINSTANCETYPE ="Source Qualifier" TOFIELD ="I_retail_price" TOINSTANCE ="EXP_TRIM" TOINSTANCETYPE ="Expression"/>
        <CONNECTOR FROMFIELD ="multiple_price" FROMINSTANCE ="SQ_FF_TEKLYNX" FROMINSTANCETYPE ="Source Qualifier" TOFIELD ="I_multiple_price" TOINSTANCE ="EXP_TRIM" TOINSTANCETYPE ="Expression"/>
        <CONNECTOR FROMFIELD ="currency" FROMINSTANCE ="SQ_FF_TEKLYNX" FROMINSTANCETYPE ="Source Qualifier" TOFIELD ="I_currency" TOINSTANCE ="EXP_TRIM" TOINSTANCETYPE ="Expression"/>
        <CONNECTOR FROMFIELD ="price_eff_dt" FROMINSTANCE ="SQ_FF_TEKLYNX" FROMINSTANCETYPE ="Source Qualifier" TOFIELD ="I_price_eff_dt" TOINSTANCE ="EXP_TRIM" TOINSTANCETYPE ="Expression"/>
        <CONNECTOR FROMFIELD ="dept" FROMINSTANCE ="SQ_FF_TEKLYNX" FROMINSTANCETYPE ="Source Qualifier" TOFIELD ="I_dept" TOINSTANCE ="EXP_TRIM" TOINSTANCETYPE ="Expression"/>
        <CONNECTOR FROMFIELD ="cust_sku" FROMINSTANCE ="SQ_FF_TEKLYNX" FROMINSTANCETYPE ="Source Qualifier" TOFIELD ="I_cust_sku" TOINSTANCE ="EXP_TRIM" TOINSTANCETYPE ="Expression"/>
        <CONNECTOR FROMFIELD ="cust_nbr" FROMINSTANCE ="SQ_FF_TEKLYNX" FROMINSTANCETYPE ="Source Qualifier" TOFIELD ="I_cust_nbr" TOINSTANCE ="EXP_TRIM" TOINSTANCETYPE ="Expression"/>
        <CONNECTOR FROMFIELD ="cust_name" FROMINSTANCE ="SQ_FF_TEKLYNX" FROMINSTANCETYPE ="Source Qualifier" TOFIELD ="I_cust_name" TOINSTANCE ="EXP_TRIM" TOINSTANCETYPE ="Expression"/>
        <CONNECTOR FROMFIELD ="material" FROMINSTANCE ="SQ_FF_TEKLYNX" FROMINSTANCETYPE ="Source Qualifier" TOFIELD ="I_material" TOINSTANCE ="EXP_TRIM" TOINSTANCETYPE ="Expression"/>
        <CONNECTOR FROMFIELD ="grid" FROMINSTANCE ="SQ_FF_TEKLYNX" FROMINSTANCETYPE ="Source Qualifier" TOFIELD ="I_grid" TOINSTANCE ="EXP_TRIM" TOINSTANCETYPE ="Expression"/>
        <CONNECTOR FROMFIELD ="timestamp" FROMINSTANCE ="SQ_FF_TEKLYNX" FROMINSTANCETYPE ="Source Qualifier" TOFIELD ="I_timestamp" TOINSTANCE ="EXP_TRIM" TOINSTANCETYPE ="Expression"/>
        <TARGETLOADORDER ORDER ="1" TARGETINSTANCE ="Teklynx_SAP_data"/>
        <ERPINFO/>
        <METADATAEXTENSION COMPONENTVERSION ="1000000" DATATYPE ="STRING" DESCRIPTION ="Conversion Mapping Name with version " DOMAINNAME ="User Defined Metadata Domain" ISCLIENTEDITABLE ="YES" ISCLIENTVISIBLE ="YES" ISREUSABLE ="NO" ISSHAREREAD ="NO" ISSHAREWRITE ="NO" MAXLENGTH ="256" NAME ="CONV_MAP_NAME" VALUE =" Teklynx_SAP_Data_Extract v1.0" VENDORNAME ="INFORMATICA"/>
    </MAPPING>
    <CONFIG DESCRIPTION ="Default session configuration object" ISDEFAULT ="YES" NAME ="default_session_config" VERSIONNUMBER ="1">
        <ATTRIBUTE NAME ="Advanced" VALUE =""/>
        <ATTRIBUTE NAME ="Constraint based load ordering" VALUE ="NO"/>
        <ATTRIBUTE NAME ="Cache LOOKUP() function" VALUE ="YES"/>
        <ATTRIBUTE NAME ="Default buffer block size" VALUE ="Auto"/>
        <ATTRIBUTE NAME ="Line Sequential buffer length" VALUE ="1024"/>
        <ATTRIBUTE NAME ="Maximum Memory Allowed For Auto Memory Attributes" VALUE ="512MB"/>
        <ATTRIBUTE NAME ="Maximum Percentage of Total Memory Allowed For Auto Memory Attributes" VALUE ="5"/>
        <ATTRIBUTE NAME ="Additional Concurrent Pipelines for Lookup Cache Creation" VALUE ="Auto"/>
        <ATTRIBUTE NAME ="Custom Properties" VALUE =""/>
        <ATTRIBUTE NAME ="Pre-build lookup cache" VALUE ="Auto"/>
        <ATTRIBUTE NAME ="Optimization Level" VALUE ="Medium"/>
        <ATTRIBUTE NAME ="DateTime Format String" VALUE ="MM/DD/YYYY HH24:MI:SS.US"/>
        <ATTRIBUTE NAME ="Pre 85 Timestamp Compatibility" VALUE ="NO"/>
        <ATTRIBUTE NAME ="Log Options" VALUE ="0"/>
        <ATTRIBUTE NAME ="Save session log by" VALUE ="Session runs"/>
        <ATTRIBUTE NAME ="Save session log for these runs" VALUE ="9"/>
        <ATTRIBUTE NAME ="Session Log File Max Size" VALUE ="0"/>
        <ATTRIBUTE NAME ="Session Log File Max Time Period" VALUE ="0"/>
        <ATTRIBUTE NAME ="Maximum Partial Session Log Files" VALUE ="1"/>
        <ATTRIBUTE NAME ="Writer Commit Statistics Log Frequency" VALUE ="1"/>
        <ATTRIBUTE NAME ="Writer Commit Statistics Log Interval" VALUE ="0"/>
        <ATTRIBUTE NAME ="Error handling" VALUE =""/>
        <ATTRIBUTE NAME ="Stop on errors" VALUE ="1"/>
        <ATTRIBUTE NAME ="Override tracing" VALUE ="None"/>
        <ATTRIBUTE NAME ="On Stored Procedure error" VALUE ="Stop"/>
        <ATTRIBUTE NAME ="On Pre-session command task error" VALUE ="Stop"/>
        <ATTRIBUTE NAME ="On Pre-Post SQL error" VALUE ="Stop"/>
        <ATTRIBUTE NAME ="Enable Recovery" VALUE ="NO"/>
        <ATTRIBUTE NAME ="Error Log Type" VALUE ="None"/>
        <ATTRIBUTE NAME ="Error Log Table Name Prefix" VALUE =""/>
        <ATTRIBUTE NAME ="Error Log File Name" VALUE ="PMError.log"/>
        <ATTRIBUTE NAME ="Log Source Row Data" VALUE ="NO"/>
        <ATTRIBUTE NAME ="Data Column Delimiter" VALUE ="|"/>
        <ATTRIBUTE NAME ="Partitioning Options" VALUE =""/>
        <ATTRIBUTE NAME ="Dynamic Partitioning" VALUE ="Disabled"/>
        <ATTRIBUTE NAME ="Number of Partitions" VALUE ="1"/>
        <ATTRIBUTE NAME ="Multiplication Factor" VALUE ="Auto"/>
        <ATTRIBUTE NAME ="Session on Grid" VALUE =""/>
        <ATTRIBUTE NAME ="Is Enabled" VALUE ="NO"/>
    </CONFIG>
    <SESSION DESCRIPTION ="This session Is used to load a data into TEKLYNX_SAP_DATA table" ISVALID ="YES" MAPPINGNAME ="m_TEKLYNX_SAP_DATA_LOAD" NAME ="s_m_TEKLYNX_SAP_DATA_LOAD" REUSABLE ="YES" SORTORDER ="Binary" VERSIONNUMBER ="1">
        <SESSTRANSFORMATIONINST ISREPARTITIONPOINT ="YES" PARTITIONTYPE ="PASS THROUGH" PIPELINE ="1" SINSTANCENAME ="Teklynx_SAP_data" STAGE ="1" TRANSFORMATIONNAME ="Teklynx_SAP_data" TRANSFORMATIONTYPE ="Target Definition">
            <ATTRIBUTE NAME ="Table Name Prefix" VALUE ="dbo"/>
        </SESSTRANSFORMATIONINST>
        <SESSTRANSFORMATIONINST ISREPARTITIONPOINT ="YES" PARTITIONTYPE ="PASS THROUGH" PIPELINE ="1" SINSTANCENAME ="SQ_FF_TEKLYNX" STAGE ="2" TRANSFORMATIONNAME ="SQ_FF_TEKLYNX" TRANSFORMATIONTYPE ="Source Qualifier"/>
        <SESSTRANSFORMATIONINST ISREPARTITIONPOINT ="NO" PIPELINE ="1" SINSTANCENAME ="EXP_TRIM" STAGE ="2" TRANSFORMATIONNAME ="EXP_TRIM" TRANSFORMATIONTYPE ="Expression">
            <PARTITION DESCRIPTION ="" NAME ="Partition #1"/>
        </SESSTRANSFORMATIONINST>
        <SESSTRANSFORMATIONINST ISREPARTITIONPOINT ="NO" PIPELINE ="0" SINSTANCENAME ="FF_TEKLYNX" STAGE ="0" TRANSFORMATIONNAME ="FF_TEKLYNX" TRANSFORMATIONTYPE ="Source Definition">
            <FLATFILE CODEPAGE ="MS1252" CONSECDELIMITERSASONE ="NO" DELIMITED ="NO" DELIMITERS ="," ESCAPE_CHARACTER ="" KEEPESCAPECHAR ="NO" LINESEQUENTIAL ="NO" MULTIDELIMITERSASAND ="YES" NULLCHARTYPE ="ASCII" NULL_CHARACTER ="*" PADBYTES ="0" QUOTE_CHARACTER ="DOUBLE" REPEATABLE ="NO" ROWDELIMITER ="0" SKIPROWS ="0" STRIPTRAILINGBLANKS ="NO"/>
        </SESSTRANSFORMATIONINST>
        <CONFIGREFERENCE REFOBJECTNAME ="default_session_config" TYPE ="Session config">
            <ATTRIBUTE NAME ="Save session log for these runs" VALUE ="9"/>
            <ATTRIBUTE NAME ="Stop on errors" VALUE ="0"/>
        </CONFIGREFERENCE>
        <SESSIONEXTENSION NAME ="Relational Writer" SINSTANCENAME ="Teklynx_SAP_data" SUBTYPE ="Relational Writer" TRANSFORMATIONTYPE ="Target Definition" TYPE ="WRITER">
            <CONNECTIONREFERENCE CNXREFNAME ="DB Connection" CONNECTIONNAME ="Teklynx" CONNECTIONNUMBER ="1" CONNECTIONSUBTYPE ="Microsoft SQL Server" CONNECTIONTYPE ="Relational" VARIABLE =""/>
            <ATTRIBUTE NAME ="Target load type" VALUE ="Normal"/>
            <ATTRIBUTE NAME ="Insert" VALUE ="YES"/>
            <ATTRIBUTE NAME ="Update as Update" VALUE ="NO"/>
            <ATTRIBUTE NAME ="Update as Insert" VALUE ="NO"/>
            <ATTRIBUTE NAME ="Update else Insert" VALUE ="NO"/>
            <ATTRIBUTE NAME ="Delete" VALUE ="NO"/>
            <ATTRIBUTE NAME ="Truncate target table option" VALUE ="YES"/>
            <ATTRIBUTE NAME ="Reject file directory" VALUE ="$PMBadFileDir&#x5c;SUPPLY_CHAIN_BI&#x5c;BAD&#x5c;"/>
            <ATTRIBUTE NAME ="Reject filename" VALUE ="s_m_TEKLYNX_SAP_DATA_LOAD.bad"/>
        </SESSIONEXTENSION>
        <SESSIONEXTENSION NAME ="File Reader" SINSTANCENAME ="SQ_FF_TEKLYNX" SUBTYPE ="File Reader" TRANSFORMATIONTYPE ="Source Qualifier" TYPE ="READER"/>
        <SESSIONEXTENSION DSQINSTNAME ="SQ_FF_TEKLYNX" DSQINSTTYPE ="Source Qualifier" NAME ="File Reader" SINSTANCENAME ="FF_TEKLYNX" SUBTYPE ="File Reader" TRANSFORMATIONTYPE ="Source Definition" TYPE ="READER">
            <CONNECTIONREFERENCE CNXREFNAME ="Connection" CONNECTIONNAME ="" CONNECTIONNUMBER ="1" CONNECTIONSUBTYPE ="" CONNECTIONTYPE ="" VARIABLE =""/>
            <ATTRIBUTE NAME ="Input Type" VALUE ="File"/>
            <ATTRIBUTE NAME ="Concurrent read partitioning" VALUE ="Optimize throughput"/>
            <ATTRIBUTE NAME ="Command Type" VALUE ="Command Generating Data"/>
            <ATTRIBUTE NAME ="Source filetype" VALUE ="Direct"/>
            <ATTRIBUTE NAME ="Source file directory" VALUE ="$PMSourceFileDir&#x5c;SUPPLY_CHAIN_BI&#x5c;SRC&#x5c;"/>
            <ATTRIBUTE NAME ="Source filename" VALUE ="Teklynx.dat"/>
            <ATTRIBUTE NAME ="Command" VALUE =""/>
            <ATTRIBUTE NAME ="File Reader Truncate String Null" VALUE ="NO"/>
            <ATTRIBUTE NAME ="Codepage Parameter" VALUE =""/>
        </SESSIONEXTENSION>
        <ATTRIBUTE NAME ="General Options" VALUE =""/>
        <ATTRIBUTE NAME ="Write Backward Compatible Session Log File" VALUE ="YES"/>
        <ATTRIBUTE NAME ="Session Log File Name" VALUE ="s_m_TEKLYNX_SAP_DATA_LOAD.log"/>
        <ATTRIBUTE NAME ="Session Log File directory" VALUE ="$PMSessionLogDir&#x5c;SUPPLY_CHAIN_BI&#x5c;LOG&#x5c;"/>
        <ATTRIBUTE NAME ="Parameter Filename" VALUE =""/>
        <ATTRIBUTE NAME ="Enable Test Load" VALUE ="NO"/>
        <ATTRIBUTE NAME ="$Source connection value" VALUE =""/>
        <ATTRIBUTE NAME ="$Target connection value" VALUE =""/>
        <ATTRIBUTE NAME ="Treat source rows as" VALUE ="Insert"/>
        <ATTRIBUTE NAME ="Commit Type" VALUE ="Target"/>
        <ATTRIBUTE NAME ="Commit Interval" VALUE ="10000"/>
        <ATTRIBUTE NAME ="Commit On End Of File" VALUE ="YES"/>
        <ATTRIBUTE NAME ="Rollback Transactions on Errors" VALUE ="NO"/>
        <ATTRIBUTE NAME ="Recovery Strategy" VALUE ="Restart task"/>
        <ATTRIBUTE NAME ="Java Classpath" VALUE =""/>
        <ATTRIBUTE NAME ="Performance" VALUE =""/>
        <ATTRIBUTE NAME ="DTM buffer size" VALUE ="Auto"/>
        <ATTRIBUTE NAME ="Collect performance data" VALUE ="NO"/>
        <ATTRIBUTE NAME ="Write performance data to repository" VALUE ="NO"/>
        <ATTRIBUTE NAME ="Incremental Aggregation" VALUE ="NO"/>
        <ATTRIBUTE NAME ="Enable high precision" VALUE ="NO"/>
        <ATTRIBUTE NAME ="Session retry on deadlock" VALUE ="NO"/>
        <ATTRIBUTE NAME ="Pushdown Optimization" VALUE ="None"/>
        <ATTRIBUTE NAME ="Allow Temporary View for Pushdown" VALUE ="NO"/>
        <ATTRIBUTE NAME ="Allow Temporary Sequence for Pushdown" VALUE ="NO"/>
        <ATTRIBUTE NAME ="Allow Pushdown for User Incompatible Connections" VALUE ="NO"/>
        <METADATAEXTENSION DATATYPE ="STRING" DESCRIPTION ="Conversion Mapping  Name with version " DOMAINNAME ="User Defined Metadata Domain" ISCLIENTEDITABLE ="YES" ISCLIENTVISIBLE ="YES" ISREUSABLE ="NO" ISSHAREREAD ="NO" ISSHAREWRITE ="NO" MAXLENGTH ="256" NAME ="CONV_MAP_NAME" VALUE ="Teklynx_SAP_Data_Extract v1.0" VENDORNAME ="INFORMATICA"/>
    </SESSION>
    <WORKFLOW DESCRIPTION ="This workflow Is used to load a data into TEKLYNX_SAP_DATA table" ISENABLED ="YES" ISRUNNABLESERVICE ="NO" ISSERVICE ="NO" ISVALID ="YES" NAME ="wf_s_m_TEKLYNX_SAP_DATA_LOAD" REUSABLE_SCHEDULER ="NO" SCHEDULERNAME ="Scheduler" SERVERNAME ="Domain10_PRD_Int_Svc" SERVER_DOMAINNAME ="Domain10_PRD" SUSPEND_ON_ERROR ="NO" TASKS_MUST_RUN_ON_SERVER ="NO" VERSIONNUMBER ="1">
        <SCHEDULER DESCRIPTION ="" NAME ="Scheduler" REUSABLE ="NO" VERSIONNUMBER ="1">
            <SCHEDULEINFO SCHEDULETYPE ="ONDEMAND"/>
        </SCHEDULER>
        <TASK DESCRIPTION ="" NAME ="Start" REUSABLE ="NO" TYPE ="Start" VERSIONNUMBER ="1"/>
        <TASKINSTANCE DESCRIPTION ="" ISENABLED ="YES" NAME ="Start" REUSABLE ="NO" TASKNAME ="Start" TASKTYPE ="Start"/>
        <TASKINSTANCE DESCRIPTION ="This session Is used to load a data into TEKLYNX_SAP_DATA table" FAIL_PARENT_IF_INSTANCE_DID_NOT_RUN ="YES" FAIL_PARENT_IF_INSTANCE_FAILS ="YES" ISENABLED ="YES" NAME ="s_m_TEKLYNX_SAP_DATA_LOAD" REUSABLE ="YES" TASKNAME ="s_m_TEKLYNX_SAP_DATA_LOAD" TASKTYPE ="Session" TREAT_INPUTLINK_AS_AND ="NO"/>
        <WORKFLOWLINK CONDITION ="" FROMTASK ="Start" TOTASK ="s_m_TEKLYNX_SAP_DATA_LOAD"/>
        <WORKFLOWVARIABLE DATATYPE ="date/time" DEFAULTVALUE ="" DESCRIPTION ="The time this task started" ISNULL ="NO" ISPERSISTENT ="NO" NAME ="$Start.StartTime" USERDEFINED ="NO"/>
        <WORKFLOWVARIABLE DATATYPE ="date/time" DEFAULTVALUE ="" DESCRIPTION ="The time this task completed" ISNULL ="NO" ISPERSISTENT ="NO" NAME ="$Start.EndTime" USERDEFINED ="NO"/>
        <WORKFLOWVARIABLE DATATYPE ="integer" DEFAULTVALUE ="" DESCRIPTION ="Status of this task&apos;s execution" ISNULL ="NO" ISPERSISTENT ="NO" NAME ="$Start.Status" USERDEFINED ="NO"/>
        <WORKFLOWVARIABLE DATATYPE ="integer" DEFAULTVALUE ="" DESCRIPTION ="Status of the previous task that is not disabled" ISNULL ="NO" ISPERSISTENT ="NO" NAME ="$Start.PrevTaskStatus" USERDEFINED ="NO"/>
        <WORKFLOWVARIABLE DATATYPE ="integer" DEFAULTVALUE ="" DESCRIPTION ="Error code for this task&apos;s execution" ISNULL ="NO" ISPERSISTENT ="NO" NAME ="$Start.ErrorCode" USERDEFINED ="NO"/>
        <WORKFLOWVARIABLE DATATYPE ="string" DEFAULTVALUE ="" DESCRIPTION ="Error message for this task&apos;s execution" ISNULL ="NO" ISPERSISTENT ="NO" NAME ="$Start.ErrorMsg" USERDEFINED ="NO"/>
        <WORKFLOWVARIABLE DATATYPE ="date/time" DEFAULTVALUE ="" DESCRIPTION ="The time this task started" ISNULL ="NO" ISPERSISTENT ="NO" NAME ="$s_m_TEKLYNX_SAP_DATA_LOAD.StartTime" USERDEFINED ="NO"/>
        <WORKFLOWVARIABLE DATATYPE ="date/time" DEFAULTVALUE ="" DESCRIPTION ="The time this task completed" ISNULL ="NO" ISPERSISTENT ="NO" NAME ="$s_m_TEKLYNX_SAP_DATA_LOAD.EndTime" USERDEFINED ="NO"/>
        <WORKFLOWVARIABLE DATATYPE ="integer" DEFAULTVALUE ="" DESCRIPTION ="Status of this task&apos;s execution" ISNULL ="NO" ISPERSISTENT ="NO" NAME ="$s_m_TEKLYNX_SAP_DATA_LOAD.Status" USERDEFINED ="NO"/>
        <WORKFLOWVARIABLE DATATYPE ="integer" DEFAULTVALUE ="" DESCRIPTION ="Status of the previous task that is not disabled" ISNULL ="NO" ISPERSISTENT ="NO" NAME ="$s_m_TEKLYNX_SAP_DATA_LOAD.PrevTaskStatus" USERDEFINED ="NO"/>
        <WORKFLOWVARIABLE DATATYPE ="integer" DEFAULTVALUE ="" DESCRIPTION ="Error code for this task&apos;s execution" ISNULL ="NO" ISPERSISTENT ="NO" NAME ="$s_m_TEKLYNX_SAP_DATA_LOAD.ErrorCode" USERDEFINED ="NO"/>
        <WORKFLOWVARIABLE DATATYPE ="string" DEFAULTVALUE ="" DESCRIPTION ="Error message for this task&apos;s execution" ISNULL ="NO" ISPERSISTENT ="NO" NAME ="$s_m_TEKLYNX_SAP_DATA_LOAD.ErrorMsg" USERDEFINED ="NO"/>
        <WORKFLOWVARIABLE DATATYPE ="integer" DEFAULTVALUE ="" DESCRIPTION ="Rows successfully read" ISNULL ="NO" ISPERSISTENT ="NO" NAME ="$s_m_TEKLYNX_SAP_DATA_LOAD.SrcSuccessRows" USERDEFINED ="NO"/>
        <WORKFLOWVARIABLE DATATYPE ="integer" DEFAULTVALUE ="" DESCRIPTION ="Rows failed to read" ISNULL ="NO" ISPERSISTENT ="NO" NAME ="$s_m_TEKLYNX_SAP_DATA_LOAD.SrcFailedRows" USERDEFINED ="NO"/>
        <WORKFLOWVARIABLE DATATYPE ="integer" DEFAULTVALUE ="" DESCRIPTION ="Rows successfully loaded" ISNULL ="NO" ISPERSISTENT ="NO" NAME ="$s_m_TEKLYNX_SAP_DATA_LOAD.TgtSuccessRows" USERDEFINED ="NO"/>
        <WORKFLOWVARIABLE DATATYPE ="integer" DEFAULTVALUE ="" DESCRIPTION ="Rows failed to load" ISNULL ="NO" ISPERSISTENT ="NO" NAME ="$s_m_TEKLYNX_SAP_DATA_LOAD.TgtFailedRows" USERDEFINED ="NO"/>
        <WORKFLOWVARIABLE DATATYPE ="integer" DEFAULTVALUE ="" DESCRIPTION ="Total number of transformation errors" ISNULL ="NO" ISPERSISTENT ="NO" NAME ="$s_m_TEKLYNX_SAP_DATA_LOAD.TotalTransErrors" USERDEFINED ="NO"/>
        <WORKFLOWVARIABLE DATATYPE ="integer" DEFAULTVALUE ="" DESCRIPTION ="First error code" ISNULL ="NO" ISPERSISTENT ="NO" NAME ="$s_m_TEKLYNX_SAP_DATA_LOAD.FirstErrorCode" USERDEFINED ="NO"/>
        <WORKFLOWVARIABLE DATATYPE ="string" DEFAULTVALUE ="" DESCRIPTION ="First error message" ISNULL ="NO" ISPERSISTENT ="NO" NAME ="$s_m_TEKLYNX_SAP_DATA_LOAD.FirstErrorMsg" USERDEFINED ="NO"/>
        <ATTRIBUTE NAME ="Parameter Filename" VALUE =""/>
        <ATTRIBUTE NAME ="Write Backward Compatible Workflow Log File" VALUE ="YES"/>
        <ATTRIBUTE NAME ="Workflow Log File Name" VALUE ="wf_s_m_TEKLYNX_SAP_DATA_LOAD.log"/>
        <ATTRIBUTE NAME ="Workflow Log File Directory" VALUE ="$PMWorkflowLogDir&#x5c;SUPPLY_CHAIN_BI&#x5c;LOG&#x5c;"/>
        <ATTRIBUTE NAME ="Save Workflow log by" VALUE ="By runs"/>
        <ATTRIBUTE NAME ="Save workflow log for these runs" VALUE ="9"/>
        <ATTRIBUTE NAME ="Service Name" VALUE =""/>
        <ATTRIBUTE NAME ="Service Timeout" VALUE ="0"/>
        <ATTRIBUTE NAME ="Is Service Visible" VALUE ="NO"/>
        <ATTRIBUTE NAME ="Is Service Protected" VALUE ="NO"/>
        <ATTRIBUTE NAME ="Fail task after wait time" VALUE ="0"/>
        <ATTRIBUTE NAME ="Enable HA recovery" VALUE ="NO"/>
        <ATTRIBUTE NAME ="Automatically recover terminated tasks" VALUE ="NO"/>
        <ATTRIBUTE NAME ="Service Level Name" VALUE ="Default"/>
        <ATTRIBUTE NAME ="Allow concurrent run with unique run instance name" VALUE ="NO"/>
        <ATTRIBUTE NAME ="Allow concurrent run with same run instance name" VALUE ="NO"/>
        <ATTRIBUTE NAME ="Maximum number of concurrent runs" VALUE ="0"/>
        <ATTRIBUTE NAME ="Assigned Web Services Hubs" VALUE =""/>
        <ATTRIBUTE NAME ="Maximum number of concurrent runs per Hub" VALUE ="1000"/>
        <ATTRIBUTE NAME ="Expected Service Time" VALUE ="1"/>
        <METADATAEXTENSION DATATYPE ="STRING" DESCRIPTION ="Conversion Mapping Name with version " DOMAINNAME ="User Defined Metadata Domain" ISCLIENTEDITABLE ="YES" ISCLIENTVISIBLE ="YES" ISREUSABLE ="NO" ISSHAREREAD ="NO" ISSHAREWRITE ="NO" MAXLENGTH ="256" NAME ="CONV_MAP_NAME" VALUE =" Teklynx_SAP_Data_Extract v1.0" VENDORNAME ="INFORMATICA"/>
        <METADATAEXTENSION DATATYPE ="STRING" DESCRIPTION ="" DOMAINNAME ="User Defined Metadata Domain" ISCLIENTEDITABLE ="YES" ISCLIENTVISIBLE ="YES" ISREUSABLE ="NO" ISSHAREREAD ="NO" ISSHAREWRITE ="NO" MAXLENGTH ="256" NAME ="Extension" VALUE ="CM - MarginLoss - stgMarginLossExpenseToStgFactSalesNew v1.0" VENDORNAME ="INFORMATICA"/>
    </WORKFLOW>
</FOLDER>
</REPOSITORY>
</POWERMART>