<?xml version="1.0" encoding="Windows-1252"?>
<!DOCTYPE POWERMART SYSTEM "powrmart.dtd">
<POWERMART CREATION_DATE="10/09/2024 09:52:36" REPOSITORY_VERSION="187.96">
<REPOSITORY NAME="Domain10_Rep_Svc_Prd" VERSION="187" CODEPAGE="MS1252" DATABASETYPE="Microsoft SQL Server">
<FOLDER NAME="SUPPLY_CHAIN_BI" GROUP="" OWNER="Administrator" SHARED="NOTSHARED" DESCRIPTION="" PERMISSIONS="rwx---r--" UUID="c048e0d4-8833-4f61-bdc8-10cb41aa67f1">
    <SOURCE BUSINESSNAME ="" DATABASETYPE ="DB2" DBDNAME ="HQ400U" DESCRIPTION ="3090 Assortment Style/Color extract" NAME ="OPP1040" OBJECTVERSION ="1" OWNERNAME ="UOPLIB" VERSIONNUMBER ="1">
        <SOURCEFIELD BUSINESSNAME ="" DATATYPE ="char" DESCRIPTION ="ASSORTMENT STYLE/COL" FIELDNUMBER ="1" FIELDPROPERTY ="0" FIELDTYPE ="ELEMITEM" HIDDEN ="NO" KEYTYPE ="NOT A KEY" LENGTH ="0" LEVEL ="0" NAME ="ASSTCL" NULLABLE ="NOTNULL" OCCURS ="0" OFFSET ="0" PHYSICALLENGTH ="6" PHYSICALOFFSET ="0" PICTURETEXT ="" PRECISION ="6" SCALE ="0" USAGE_FLAGS =""/>
        <SOURCEFIELD BUSINESSNAME ="" DATATYPE ="char" DESCRIPTION ="COMPONENT STYLE" FIELDNUMBER ="2" FIELDPROPERTY ="0" FIELDTYPE ="ELEMITEM" HIDDEN ="NO" KEYTYPE ="NOT A KEY" LENGTH ="0" LEVEL ="0" NAME ="ASCMST" NULLABLE ="NOTNULL" OCCURS ="0" OFFSET ="0" PHYSICALLENGTH ="6" PHYSICALOFFSET ="6" PICTURETEXT ="" PRECISION ="6" SCALE ="0" USAGE_FLAGS =""/>
        <SOURCEFIELD BUSINESSNAME ="" DATATYPE ="char" DESCRIPTION ="COMPONENT COLOR" FIELDNUMBER ="3" FIELDPROPERTY ="0" FIELDTYPE ="ELEMITEM" HIDDEN ="NO" KEYTYPE ="NOT A KEY" LENGTH ="0" LEVEL ="0" NAME ="ASCMCL" NULLABLE ="NOTNULL" OCCURS ="0" OFFSET ="0" PHYSICALLENGTH ="3" PHYSICALOFFSET ="12" PICTURETEXT ="" PRECISION ="3" SCALE ="0" USAGE_FLAGS =""/>
        <SOURCEFIELD BUSINESSNAME ="" DATATYPE ="numeric" DESCRIPTION ="COMPONENT PARTS/DOZ" FIELDNUMBER ="4" FIELDPROPERTY ="0" FIELDTYPE ="ELEMITEM" HIDDEN ="NO" KEYTYPE ="NOT A KEY" LENGTH ="4" LEVEL ="0" NAME ="ASCMPD" NULLABLE ="NOTNULL" OCCURS ="0" OFFSET ="0" PHYSICALLENGTH ="2" PHYSICALOFFSET ="15" PICTURETEXT ="" PRECISION ="2" SCALE ="0" USAGE_FLAGS =""/>
        <SOURCEFIELD BUSINESSNAME ="" DATATYPE ="char" DESCRIPTION ="ASSORTMENT PACK CODE" FIELDNUMBER ="5" FIELDPROPERTY ="0" FIELDTYPE ="ELEMITEM" HIDDEN ="NO" KEYTYPE ="NOT A KEY" LENGTH ="0" LEVEL ="0" NAME ="ASSTPK" NULLABLE ="NOTNULL" OCCURS ="0" OFFSET ="4" PHYSICALLENGTH ="1" PHYSICALOFFSET ="17" PICTURETEXT ="" PRECISION ="1" SCALE ="0" USAGE_FLAGS =""/>
        <SOURCEFIELD BUSINESSNAME ="" DATATYPE ="char" DESCRIPTION ="ASSORTMENT TYPE" FIELDNUMBER ="6" FIELDPROPERTY ="0" FIELDTYPE ="ELEMITEM" HIDDEN ="NO" KEYTYPE ="NOT A KEY" LENGTH ="0" LEVEL ="0" NAME ="ASTYPE" NULLABLE ="NOTNULL" OCCURS ="0" OFFSET ="4" PHYSICALLENGTH ="1" PHYSICALOFFSET ="18" PICTURETEXT ="" PRECISION ="1" SCALE ="0" USAGE_FLAGS =""/>
        <SOURCEFIELD BUSINESSNAME ="" DATATYPE ="char" DESCRIPTION ="ASSORTMENT SIZELINE" FIELDNUMBER ="7" FIELDPROPERTY ="0" FIELDTYPE ="ELEMITEM" HIDDEN ="NO" KEYTYPE ="NOT A KEY" LENGTH ="0" LEVEL ="0" NAME ="ASZLIN" NULLABLE ="NOTNULL" OCCURS ="0" OFFSET ="4" PHYSICALLENGTH ="1" PHYSICALOFFSET ="19" PICTURETEXT ="" PRECISION ="1" SCALE ="0" USAGE_FLAGS =""/>
        <SOURCEFIELD BUSINESSNAME ="" DATATYPE ="char" DESCRIPTION ="COMPONENT SIZELINE" FIELDNUMBER ="8" FIELDPROPERTY ="0" FIELDTYPE ="ELEMITEM" HIDDEN ="NO" KEYTYPE ="NOT A KEY" LENGTH ="0" LEVEL ="0" NAME ="ASCMSL" NULLABLE ="NOTNULL" OCCURS ="0" OFFSET ="4" PHYSICALLENGTH ="1" PHYSICALOFFSET ="20" PICTURETEXT ="" PRECISION ="1" SCALE ="0" USAGE_FLAGS =""/>
        <SOURCEFIELD BUSINESSNAME ="" DATATYPE ="numeric" DESCRIPTION ="COMPONENT PARTS/PKG" FIELDNUMBER ="9" FIELDPROPERTY ="0" FIELDTYPE ="ELEMITEM" HIDDEN ="NO" KEYTYPE ="NOT A KEY" LENGTH ="7" LEVEL ="0" NAME ="ASCMPP" NULLABLE ="NOTNULL" OCCURS ="0" OFFSET ="4" PHYSICALLENGTH ="5" PHYSICALOFFSET ="21" PICTURETEXT ="" PRECISION ="5" SCALE ="0" USAGE_FLAGS =""/>
    </SOURCE>
    <TARGET BUSINESSNAME ="" CONSTRAINT ="" DATABASETYPE ="Oracle" DESCRIPTION ="" NAME ="STG_UW_WIP_OPP1040" OBJECTVERSION ="1" TABLEOPTIONS ="" VERSIONNUMBER ="1">
        <TARGETFIELD BUSINESSNAME ="" DATATYPE ="varchar2" DESCRIPTION ="" FIELDNUMBER ="1" KEYTYPE ="NOT A KEY" NAME ="ASSORTMENT_STYLE_COL" NULLABLE ="NULL" PICTURETEXT ="" PRECISION ="6" SCALE ="0"/>
        <TARGETFIELD BUSINESSNAME ="" DATATYPE ="varchar2" DESCRIPTION ="" FIELDNUMBER ="2" KEYTYPE ="NOT A KEY" NAME ="COMPONENT_STYLE" NULLABLE ="NULL" PICTURETEXT ="" PRECISION ="6" SCALE ="0"/>
        <TARGETFIELD BUSINESSNAME ="" DATATYPE ="varchar2" DESCRIPTION ="" FIELDNUMBER ="3" KEYTYPE ="NOT A KEY" NAME ="COMPONENT_COLOR" NULLABLE ="NULL" PICTURETEXT ="" PRECISION ="3" SCALE ="0"/>
        <TARGETFIELD BUSINESSNAME ="" DATATYPE ="number(p,s)" DESCRIPTION ="" FIELDNUMBER ="4" KEYTYPE ="NOT A KEY" NAME ="COMPONENT_PARTS_DOZ" NULLABLE ="NULL" PICTURETEXT ="" PRECISION ="2" SCALE ="0"/>
        <TARGETFIELD BUSINESSNAME ="" DATATYPE ="varchar2" DESCRIPTION ="" FIELDNUMBER ="5" KEYTYPE ="NOT A KEY" NAME ="ASSORTMENT_PACK_CODE" NULLABLE ="NULL" PICTURETEXT ="" PRECISION ="1" SCALE ="0"/>
        <TARGETFIELD BUSINESSNAME ="" DATATYPE ="varchar2" DESCRIPTION ="" FIELDNUMBER ="6" KEYTYPE ="NOT A KEY" NAME ="ASSORTMENT_TYPE" NULLABLE ="NULL" PICTURETEXT ="" PRECISION ="1" SCALE ="0"/>
        <TARGETFIELD BUSINESSNAME ="" DATATYPE ="varchar2" DESCRIPTION ="" FIELDNUMBER ="7" KEYTYPE ="NOT A KEY" NAME ="ASSORTMENT_SIZE_LINE" NULLABLE ="NULL" PICTURETEXT ="" PRECISION ="1" SCALE ="0"/>
        <TARGETFIELD BUSINESSNAME ="" DATATYPE ="varchar2" DESCRIPTION ="" FIELDNUMBER ="8" KEYTYPE ="NOT A KEY" NAME ="COMPONENT_SIZE_LINE" NULLABLE ="NULL" PICTURETEXT ="" PRECISION ="1" SCALE ="0"/>
        <TARGETFIELD BUSINESSNAME ="" DATATYPE ="number(p,s)" DESCRIPTION ="" FIELDNUMBER ="9" KEYTYPE ="NOT A KEY" NAME ="COMPONENT_PARTS_PKG" NULLABLE ="NULL" PICTURETEXT ="" PRECISION ="5" SCALE ="0"/>
        <TARGETFIELD BUSINESSNAME ="" DATATYPE ="date" DESCRIPTION ="" FIELDNUMBER ="10" KEYTYPE ="NOT A KEY" NAME ="PROCESSED_TIMESTAMP" NULLABLE ="NOTNULL" PICTURETEXT ="" PRECISION ="19" SCALE ="0"/>
        <TARGETFIELD BUSINESSNAME ="" DATATYPE ="varchar2" DESCRIPTION ="" FIELDNUMBER ="11" KEYTYPE ="NOT A KEY" NAME ="PROCESSED_USERID" NULLABLE ="NOTNULL" PICTURETEXT ="" PRECISION ="30" SCALE ="0"/>
        <TARGETFIELD BUSINESSNAME ="" DATATYPE ="varchar2" DESCRIPTION ="" FIELDNUMBER ="12" KEYTYPE ="NOT A KEY" NAME ="PROCESSED_FLAG" NULLABLE ="NOTNULL" PICTURETEXT ="" PRECISION ="1" SCALE ="0"/>
    </TARGET>
    <MAPPING DESCRIPTION ="Mapping to load STG_UW_WIP_OPP1040 from OPP1040 " ISVALID ="YES" NAME ="m_STG_UW_WIP_OPP1040" OBJECTVERSION ="1" VERSIONNUMBER ="1">
        <TRANSFORMATION DESCRIPTION ="Source Qualifier to pull the records from the source OPP1040" NAME ="SQ_OPP1040" OBJECTVERSION ="1" REUSABLE ="NO" TYPE ="Source Qualifier" VERSIONNUMBER ="1">
            <TRANSFORMFIELD DATATYPE ="string" DEFAULTVALUE ="" DESCRIPTION ="ASSORTMENT STYLE/COL" NAME ="ASSTCL" PICTURETEXT ="" PORTTYPE ="INPUT/OUTPUT" PRECISION ="6" SCALE ="0"/>
            <TRANSFORMFIELD DATATYPE ="string" DEFAULTVALUE ="" DESCRIPTION ="COMPONENT STYLE" NAME ="ASCMST" PICTURETEXT ="" PORTTYPE ="INPUT/OUTPUT" PRECISION ="6" SCALE ="0"/>
            <TRANSFORMFIELD DATATYPE ="string" DEFAULTVALUE ="" DESCRIPTION ="COMPONENT COLOR" NAME ="ASCMCL" PICTURETEXT ="" PORTTYPE ="INPUT/OUTPUT" PRECISION ="3" SCALE ="0"/>
            <TRANSFORMFIELD DATATYPE ="decimal" DEFAULTVALUE ="" DESCRIPTION ="COMPONENT PARTS/DOZ" NAME ="ASCMPD" PICTURETEXT ="" PORTTYPE ="INPUT/OUTPUT" PRECISION ="2" SCALE ="0"/>
            <TRANSFORMFIELD DATATYPE ="string" DEFAULTVALUE ="" DESCRIPTION ="ASSORTMENT PACK CODE" NAME ="ASSTPK" PICTURETEXT ="" PORTTYPE ="INPUT/OUTPUT" PRECISION ="1" SCALE ="0"/>
            <TRANSFORMFIELD DATATYPE ="string" DEFAULTVALUE ="" DESCRIPTION ="ASSORTMENT TYPE" NAME ="ASTYPE" PICTURETEXT ="" PORTTYPE ="INPUT/OUTPUT" PRECISION ="1" SCALE ="0"/>
            <TRANSFORMFIELD DATATYPE ="string" DEFAULTVALUE ="" DESCRIPTION ="ASSORTMENT SIZELINE" NAME ="ASZLIN" PICTURETEXT ="" PORTTYPE ="INPUT/OUTPUT" PRECISION ="1" SCALE ="0"/>
            <TRANSFORMFIELD DATATYPE ="string" DEFAULTVALUE ="" DESCRIPTION ="COMPONENT SIZELINE" NAME ="ASCMSL" PICTURETEXT ="" PORTTYPE ="INPUT/OUTPUT" PRECISION ="1" SCALE ="0"/>
            <TRANSFORMFIELD DATATYPE ="decimal" DEFAULTVALUE ="" DESCRIPTION ="COMPONENT PARTS/PKG" NAME ="ASCMPP" PICTURETEXT ="" PORTTYPE ="INPUT/OUTPUT" PRECISION ="5" SCALE ="0"/>
            <TABLEATTRIBUTE NAME ="Sql Query" VALUE ="SELECT OPP1040.ASSTCL, OPP1040.ASCMST, OPP1040.ASCMCL, OPP1040.ASCMPD, OPP1040.ASSTPK, OPP1040.ASTYPE, OPP1040.ASZLIN, OPP1040.ASCMSL, OPP1040.ASCMPP &#xD;&#xA;FROM&#xD;&#xA; UOPLIB.OPP1040 OPP1040"/>
            <TABLEATTRIBUTE NAME ="User Defined Join" VALUE =""/>
            <TABLEATTRIBUTE NAME ="Source Filter" VALUE =""/>
            <TABLEATTRIBUTE NAME ="Number Of Sorted Ports" VALUE ="0"/>
            <TABLEATTRIBUTE NAME ="Tracing Level" VALUE ="Normal"/>
            <TABLEATTRIBUTE NAME ="Select Distinct" VALUE ="NO"/>
            <TABLEATTRIBUTE NAME ="Is Partitionable" VALUE ="NO"/>
            <TABLEATTRIBUTE NAME ="Pre SQL" VALUE =""/>
            <TABLEATTRIBUTE NAME ="Post SQL" VALUE =""/>
            <TABLEATTRIBUTE NAME ="Output is deterministic" VALUE ="NO"/>
            <TABLEATTRIBUTE NAME ="Output is repeatable" VALUE ="Never"/>
        </TRANSFORMATION>
        <TRANSFORMATION DESCRIPTION ="Expression to set some default target values" NAME ="EXP_STG_UW_WIP_OPP1040" OBJECTVERSION ="1" REUSABLE ="NO" TYPE ="Expression" VERSIONNUMBER ="1">
            <TRANSFORMFIELD DATATYPE ="string" DEFAULTVALUE ="" DESCRIPTION ="ASSORTMENT STYLE/COL" NAME ="I_ASSTCL" PICTURETEXT ="" PORTTYPE ="INPUT" PRECISION ="6" SCALE ="0"/>
            <TRANSFORMFIELD DATATYPE ="string" DEFAULTVALUE ="" DESCRIPTION ="COMPONENT STYLE" NAME ="I_ASCMST" PICTURETEXT ="" PORTTYPE ="INPUT" PRECISION ="6" SCALE ="0"/>
            <TRANSFORMFIELD DATATYPE ="string" DEFAULTVALUE ="" DESCRIPTION ="COMPONENT COLOR" NAME ="I_ASCMCL" PICTURETEXT ="" PORTTYPE ="INPUT" PRECISION ="3" SCALE ="0"/>
            <TRANSFORMFIELD DATATYPE ="decimal" DEFAULTVALUE ="" DESCRIPTION ="COMPONENT PARTS/DOZ" NAME ="I_ASCMPD" PICTURETEXT ="" PORTTYPE ="INPUT" PRECISION ="2" SCALE ="0"/>
            <TRANSFORMFIELD DATATYPE ="string" DEFAULTVALUE ="" DESCRIPTION ="ASSORTMENT PACK CODE" NAME ="I_ASSTPK" PICTURETEXT ="" PORTTYPE ="INPUT" PRECISION ="1" SCALE ="0"/>
            <TRANSFORMFIELD DATATYPE ="string" DEFAULTVALUE ="" DESCRIPTION ="ASSORTMENT TYPE" NAME ="I_ASTYPE" PICTURETEXT ="" PORTTYPE ="INPUT" PRECISION ="1" SCALE ="0"/>
            <TRANSFORMFIELD DATATYPE ="string" DEFAULTVALUE ="" DESCRIPTION ="ASSORTMENT SIZELINE" NAME ="I_ASZLIN" PICTURETEXT ="" PORTTYPE ="INPUT" PRECISION ="1" SCALE ="0"/>
            <TRANSFORMFIELD DATATYPE ="string" DEFAULTVALUE ="" DESCRIPTION ="COMPONENT SIZELINE" NAME ="I_ASCMSL" PICTURETEXT ="" PORTTYPE ="INPUT" PRECISION ="1" SCALE ="0"/>
            <TRANSFORMFIELD DATATYPE ="decimal" DEFAULTVALUE ="" DESCRIPTION ="COMPONENT PARTS/PKG" NAME ="I_ASCMPP" PICTURETEXT ="" PORTTYPE ="INPUT" PRECISION ="5" SCALE ="0"/>
            <TRANSFORMFIELD DATATYPE ="string" DEFAULTVALUE ="" DESCRIPTION ="ASSORTMENT STYLE/COL" EXPRESSION ="LTRIM(RTRIM(I_ASSTCL))" EXPRESSIONTYPE ="GENERAL" NAME ="O_ASSTCL" PICTURETEXT ="" PORTTYPE ="OUTPUT" PRECISION ="6" SCALE ="0"/>
            <TRANSFORMFIELD DATATYPE ="string" DEFAULTVALUE ="ERROR(&apos;transformation error&apos;)" DESCRIPTION ="COMPONENT STYLE" EXPRESSION ="LTRIM(RTRIM(I_ASCMST))" EXPRESSIONTYPE ="GENERAL" NAME ="O_ASCMST" PICTURETEXT ="" PORTTYPE ="OUTPUT" PRECISION ="6" SCALE ="0"/>
            <TRANSFORMFIELD DATATYPE ="string" DEFAULTVALUE ="ERROR(&apos;transformation error&apos;)" DESCRIPTION ="COMPONENT COLOR" EXPRESSION ="LTRIM(RTRIM(I_ASCMCL))" EXPRESSIONTYPE ="GENERAL" NAME ="O_ASCMCL" PICTURETEXT ="" PORTTYPE ="OUTPUT" PRECISION ="3" SCALE ="0"/>
            <TRANSFORMFIELD DATATYPE ="decimal" DEFAULTVALUE ="ERROR(&apos;transformation error&apos;)" DESCRIPTION ="COMPONENT PARTS/DOZ" EXPRESSION ="LTRIM(RTRIM(I_ASCMPD))" EXPRESSIONTYPE ="GENERAL" NAME ="O_ASCMPD" PICTURETEXT ="" PORTTYPE ="OUTPUT" PRECISION ="2" SCALE ="0"/>
            <TRANSFORMFIELD DATATYPE ="string" DEFAULTVALUE ="ERROR(&apos;transformation error&apos;)" DESCRIPTION ="ASSORTMENT PACK CODE" EXPRESSION ="LTRIM(RTRIM(I_ASSTPK))" EXPRESSIONTYPE ="GENERAL" NAME ="O_ASSTPK" PICTURETEXT ="" PORTTYPE ="OUTPUT" PRECISION ="1" SCALE ="0"/>
            <TRANSFORMFIELD DATATYPE ="string" DEFAULTVALUE ="ERROR(&apos;transformation error&apos;)" DESCRIPTION ="ASSORTMENT TYPE" EXPRESSION ="LTRIM(RTRIM(I_ASTYPE))" EXPRESSIONTYPE ="GENERAL" NAME ="O_ASTYPE" PICTURETEXT ="" PORTTYPE ="OUTPUT" PRECISION ="1" SCALE ="0"/>
            <TRANSFORMFIELD DATATYPE ="string" DEFAULTVALUE ="ERROR(&apos;transformation error&apos;)" DESCRIPTION ="ASSORTMENT SIZELINE" EXPRESSION ="LTRIM(RTRIM(I_ASZLIN))" EXPRESSIONTYPE ="GENERAL" NAME ="O_ASZLIN" PICTURETEXT ="" PORTTYPE ="OUTPUT" PRECISION ="1" SCALE ="0"/>
            <TRANSFORMFIELD DATATYPE ="string" DEFAULTVALUE ="ERROR(&apos;transformation error&apos;)" DESCRIPTION ="COMPONENT SIZELINE" EXPRESSION ="LTRIM(RTRIM(I_ASCMSL))" EXPRESSIONTYPE ="GENERAL" NAME ="O_ASCMSL" PICTURETEXT ="" PORTTYPE ="OUTPUT" PRECISION ="1" SCALE ="0"/>
            <TRANSFORMFIELD DATATYPE ="decimal" DEFAULTVALUE ="ERROR(&apos;transformation error&apos;)" DESCRIPTION ="COMPONENT PARTS/PKG" EXPRESSION ="LTRIM(RTRIM(I_ASCMPP))" EXPRESSIONTYPE ="GENERAL" NAME ="O_ASCMPP" PICTURETEXT ="" PORTTYPE ="OUTPUT" PRECISION ="5" SCALE ="0"/>
            <TRANSFORMFIELD DATATYPE ="date/time" DEFAULTVALUE ="" DESCRIPTION ="" EXPRESSION ="SESSSTARTTIME" EXPRESSIONTYPE ="GENERAL" NAME ="O_PROCESSED_TSTAMP" PICTURETEXT ="" PORTTYPE ="OUTPUT" PRECISION ="29" SCALE ="9"/>
            <TRANSFORMFIELD DATATYPE ="string" DEFAULTVALUE ="" DESCRIPTION ="" EXPRESSION ="&apos;OPP1040LOAD&apos;" EXPRESSIONTYPE ="GENERAL" NAME ="O_PROCESSED_USERID" PICTURETEXT ="" PORTTYPE ="OUTPUT" PRECISION ="30" SCALE ="0"/>
            <TRANSFORMFIELD DATATYPE ="string" DEFAULTVALUE ="" DESCRIPTION ="" EXPRESSION ="&apos;N&apos;" EXPRESSIONTYPE ="GENERAL" NAME ="O_PROCESSED_FLAG" PICTURETEXT ="" PORTTYPE ="OUTPUT" PRECISION ="1" SCALE ="0"/>
            <TABLEATTRIBUTE NAME ="Tracing Level" VALUE ="Normal"/>
        </TRANSFORMATION>
        <INSTANCE DESCRIPTION ="Target Table" NAME ="STG_UW_WIP_OPP1040" TRANSFORMATION_NAME ="STG_UW_WIP_OPP1040" TRANSFORMATION_TYPE ="Target Definition" TYPE ="TARGET"/>
        <INSTANCE DBDNAME ="HQ400U" DESCRIPTION ="Source Table" NAME ="OPP1040" TRANSFORMATION_NAME ="OPP1040" TRANSFORMATION_TYPE ="Source Definition" TYPE ="SOURCE"/>
        <INSTANCE DESCRIPTION ="Source Qualifier to pull the records from the source OPP1040" NAME ="SQ_OPP1040" REUSABLE ="NO" TRANSFORMATION_NAME ="SQ_OPP1040" TRANSFORMATION_TYPE ="Source Qualifier" TYPE ="TRANSFORMATION">
            <ASSOCIATED_SOURCE_INSTANCE NAME ="OPP1040"/>
        </INSTANCE>
        <INSTANCE DESCRIPTION ="Expression to set some default target values" NAME ="EXP_STG_UW_WIP_OPP1040" REUSABLE ="NO" TRANSFORMATION_NAME ="EXP_STG_UW_WIP_OPP1040" TRANSFORMATION_TYPE ="Expression" TYPE ="TRANSFORMATION"/>
        <CONNECTOR FROMFIELD ="O_PROCESSED_TSTAMP" FROMINSTANCE ="EXP_STG_UW_WIP_OPP1040" FROMINSTANCETYPE ="Expression" TOFIELD ="PROCESSED_TIMESTAMP" TOINSTANCE ="STG_UW_WIP_OPP1040" TOINSTANCETYPE ="Target Definition"/>
        <CONNECTOR FROMFIELD ="O_PROCESSED_USERID" FROMINSTANCE ="EXP_STG_UW_WIP_OPP1040" FROMINSTANCETYPE ="Expression" TOFIELD ="PROCESSED_USERID" TOINSTANCE ="STG_UW_WIP_OPP1040" TOINSTANCETYPE ="Target Definition"/>
        <CONNECTOR FROMFIELD ="O_PROCESSED_FLAG" FROMINSTANCE ="EXP_STG_UW_WIP_OPP1040" FROMINSTANCETYPE ="Expression" TOFIELD ="PROCESSED_FLAG" TOINSTANCE ="STG_UW_WIP_OPP1040" TOINSTANCETYPE ="Target Definition"/>
        <CONNECTOR FROMFIELD ="O_ASSTCL" FROMINSTANCE ="EXP_STG_UW_WIP_OPP1040" FROMINSTANCETYPE ="Expression" TOFIELD ="ASSORTMENT_STYLE_COL" TOINSTANCE ="STG_UW_WIP_OPP1040" TOINSTANCETYPE ="Target Definition"/>
        <CONNECTOR FROMFIELD ="O_ASCMST" FROMINSTANCE ="EXP_STG_UW_WIP_OPP1040" FROMINSTANCETYPE ="Expression" TOFIELD ="COMPONENT_STYLE" TOINSTANCE ="STG_UW_WIP_OPP1040" TOINSTANCETYPE ="Target Definition"/>
        <CONNECTOR FROMFIELD ="O_ASCMCL" FROMINSTANCE ="EXP_STG_UW_WIP_OPP1040" FROMINSTANCETYPE ="Expression" TOFIELD ="COMPONENT_COLOR" TOINSTANCE ="STG_UW_WIP_OPP1040" TOINSTANCETYPE ="Target Definition"/>
        <CONNECTOR FROMFIELD ="O_ASCMPD" FROMINSTANCE ="EXP_STG_UW_WIP_OPP1040" FROMINSTANCETYPE ="Expression" TOFIELD ="COMPONENT_PARTS_DOZ" TOINSTANCE ="STG_UW_WIP_OPP1040" TOINSTANCETYPE ="Target Definition"/>
        <CONNECTOR FROMFIELD ="O_ASSTPK" FROMINSTANCE ="EXP_STG_UW_WIP_OPP1040" FROMINSTANCETYPE ="Expression" TOFIELD ="ASSORTMENT_PACK_CODE" TOINSTANCE ="STG_UW_WIP_OPP1040" TOINSTANCETYPE ="Target Definition"/>
        <CONNECTOR FROMFIELD ="O_ASTYPE" FROMINSTANCE ="EXP_STG_UW_WIP_OPP1040" FROMINSTANCETYPE ="Expression" TOFIELD ="ASSORTMENT_TYPE" TOINSTANCE ="STG_UW_WIP_OPP1040" TOINSTANCETYPE ="Target Definition"/>
        <CONNECTOR FROMFIELD ="O_ASZLIN" FROMINSTANCE ="EXP_STG_UW_WIP_OPP1040" FROMINSTANCETYPE ="Expression" TOFIELD ="ASSORTMENT_SIZE_LINE" TOINSTANCE ="STG_UW_WIP_OPP1040" TOINSTANCETYPE ="Target Definition"/>
        <CONNECTOR FROMFIELD ="O_ASCMSL" FROMINSTANCE ="EXP_STG_UW_WIP_OPP1040" FROMINSTANCETYPE ="Expression" TOFIELD ="COMPONENT_SIZE_LINE" TOINSTANCE ="STG_UW_WIP_OPP1040" TOINSTANCETYPE ="Target Definition"/>
        <CONNECTOR FROMFIELD ="O_ASCMPP" FROMINSTANCE ="EXP_STG_UW_WIP_OPP1040" FROMINSTANCETYPE ="Expression" TOFIELD ="COMPONENT_PARTS_PKG" TOINSTANCE ="STG_UW_WIP_OPP1040" TOINSTANCETYPE ="Target Definition"/>
        <CONNECTOR FROMFIELD ="ASSTCL" FROMINSTANCE ="OPP1040" FROMINSTANCETYPE ="Source Definition" TOFIELD ="ASSTCL" TOINSTANCE ="SQ_OPP1040" TOINSTANCETYPE ="Source Qualifier"/>
        <CONNECTOR FROMFIELD ="ASCMST" FROMINSTANCE ="OPP1040" FROMINSTANCETYPE ="Source Definition" TOFIELD ="ASCMST" TOINSTANCE ="SQ_OPP1040" TOINSTANCETYPE ="Source Qualifier"/>
        <CONNECTOR FROMFIELD ="ASCMCL" FROMINSTANCE ="OPP1040" FROMINSTANCETYPE ="Source Definition" TOFIELD ="ASCMCL" TOINSTANCE ="SQ_OPP1040" TOINSTANCETYPE ="Source Qualifier"/>
        <CONNECTOR FROMFIELD ="ASCMPD" FROMINSTANCE ="OPP1040" FROMINSTANCETYPE ="Source Definition" TOFIELD ="ASCMPD" TOINSTANCE ="SQ_OPP1040" TOINSTANCETYPE ="Source Qualifier"/>
        <CONNECTOR FROMFIELD ="ASSTPK" FROMINSTANCE ="OPP1040" FROMINSTANCETYPE ="Source Definition" TOFIELD ="ASSTPK" TOINSTANCE ="SQ_OPP1040" TOINSTANCETYPE ="Source Qualifier"/>
        <CONNECTOR FROMFIELD ="ASTYPE" FROMINSTANCE ="OPP1040" FROMINSTANCETYPE ="Source Definition" TOFIELD ="ASTYPE" TOINSTANCE ="SQ_OPP1040" TOINSTANCETYPE ="Source Qualifier"/>
        <CONNECTOR FROMFIELD ="ASZLIN" FROMINSTANCE ="OPP1040" FROMINSTANCETYPE ="Source Definition" TOFIELD ="ASZLIN" TOINSTANCE ="SQ_OPP1040" TOINSTANCETYPE ="Source Qualifier"/>
        <CONNECTOR FROMFIELD ="ASCMSL" FROMINSTANCE ="OPP1040" FROMINSTANCETYPE ="Source Definition" TOFIELD ="ASCMSL" TOINSTANCE ="SQ_OPP1040" TOINSTANCETYPE ="Source Qualifier"/>
        <CONNECTOR FROMFIELD ="ASCMPP" FROMINSTANCE ="OPP1040" FROMINSTANCETYPE ="Source Definition" TOFIELD ="ASCMPP" TOINSTANCE ="SQ_OPP1040" TOINSTANCETYPE ="Source Qualifier"/>
        <CONNECTOR FROMFIELD ="ASSTCL" FROMINSTANCE ="SQ_OPP1040" FROMINSTANCETYPE ="Source Qualifier" TOFIELD ="I_ASSTCL" TOINSTANCE ="EXP_STG_UW_WIP_OPP1040" TOINSTANCETYPE ="Expression"/>
        <CONNECTOR FROMFIELD ="ASCMST" FROMINSTANCE ="SQ_OPP1040" FROMINSTANCETYPE ="Source Qualifier" TOFIELD ="I_ASCMST" TOINSTANCE ="EXP_STG_UW_WIP_OPP1040" TOINSTANCETYPE ="Expression"/>
        <CONNECTOR FROMFIELD ="ASCMCL" FROMINSTANCE ="SQ_OPP1040" FROMINSTANCETYPE ="Source Qualifier" TOFIELD ="I_ASCMCL" TOINSTANCE ="EXP_STG_UW_WIP_OPP1040" TOINSTANCETYPE ="Expression"/>
        <CONNECTOR FROMFIELD ="ASCMPD" FROMINSTANCE ="SQ_OPP1040" FROMINSTANCETYPE ="Source Qualifier" TOFIELD ="I_ASCMPD" TOINSTANCE ="EXP_STG_UW_WIP_OPP1040" TOINSTANCETYPE ="Expression"/>
        <CONNECTOR FROMFIELD ="ASSTPK" FROMINSTANCE ="SQ_OPP1040" FROMINSTANCETYPE ="Source Qualifier" TOFIELD ="I_ASSTPK" TOINSTANCE ="EXP_STG_UW_WIP_OPP1040" TOINSTANCETYPE ="Expression"/>
        <CONNECTOR FROMFIELD ="ASTYPE" FROMINSTANCE ="SQ_OPP1040" FROMINSTANCETYPE ="Source Qualifier" TOFIELD ="I_ASTYPE" TOINSTANCE ="EXP_STG_UW_WIP_OPP1040" TOINSTANCETYPE ="Expression"/>
        <CONNECTOR FROMFIELD ="ASZLIN" FROMINSTANCE ="SQ_OPP1040" FROMINSTANCETYPE ="Source Qualifier" TOFIELD ="I_ASZLIN" TOINSTANCE ="EXP_STG_UW_WIP_OPP1040" TOINSTANCETYPE ="Expression"/>
        <CONNECTOR FROMFIELD ="ASCMSL" FROMINSTANCE ="SQ_OPP1040" FROMINSTANCETYPE ="Source Qualifier" TOFIELD ="I_ASCMSL" TOINSTANCE ="EXP_STG_UW_WIP_OPP1040" TOINSTANCETYPE ="Expression"/>
        <CONNECTOR FROMFIELD ="ASCMPP" FROMINSTANCE ="SQ_OPP1040" FROMINSTANCETYPE ="Source Qualifier" TOFIELD ="I_ASCMPP" TOINSTANCE ="EXP_STG_UW_WIP_OPP1040" TOINSTANCETYPE ="Expression"/>
        <TARGETLOADORDER ORDER ="1" TARGETINSTANCE ="STG_UW_WIP_OPP1040"/>
        <ERPINFO/>
        <METADATAEXTENSION DATATYPE ="STRING" DESCRIPTION ="Conversion Mapping Name with version " DOMAINNAME ="User Defined Metadata Domain" ISCLIENTEDITABLE ="YES" ISCLIENTVISIBLE ="YES" ISREUSABLE ="NO" ISSHAREREAD ="NO" ISSHAREWRITE ="NO" MAXLENGTH ="256" NAME ="CONV_MAP_NAME" VALUE ="09/24/2009:moraffee:Conversion Mapping - UW WIP OPP1040_v1.0.xls" VENDORNAME ="INFORMATICA"/>
    </MAPPING>
    <CONFIG DESCRIPTION ="Default session configuration object" ISDEFAULT ="YES" NAME ="default_session_config" VERSIONNUMBER ="1">
        <ATTRIBUTE NAME ="Advanced" VALUE =""/>
        <ATTRIBUTE NAME ="Constraint based load ordering" VALUE ="NO"/>
        <ATTRIBUTE NAME ="Cache LOOKUP() function" VALUE ="YES"/>
        <ATTRIBUTE NAME ="Default buffer block size" VALUE ="Auto"/>
        <ATTRIBUTE NAME ="Line Sequential buffer length" VALUE ="1024"/>
        <ATTRIBUTE NAME ="Maximum Memory Allowed For Auto Memory Attributes" VALUE ="512MB"/>
        <ATTRIBUTE NAME ="Maximum Percentage of Total Memory Allowed For Auto Memory Attributes" VALUE ="5"/>
        <ATTRIBUTE NAME ="Additional Concurrent Pipelines for Lookup Cache Creation" VALUE ="Auto"/>
        <ATTRIBUTE NAME ="Custom Properties" VALUE =""/>
        <ATTRIBUTE NAME ="Pre-build lookup cache" VALUE ="Auto"/>
        <ATTRIBUTE NAME ="Optimization Level" VALUE ="Medium"/>
        <ATTRIBUTE NAME ="DateTime Format String" VALUE ="MM/DD/YYYY HH24:MI:SS.US"/>
        <ATTRIBUTE NAME ="Pre 85 Timestamp Compatibility" VALUE ="NO"/>
        <ATTRIBUTE NAME ="Log Options" VALUE ="0"/>
        <ATTRIBUTE NAME ="Save session log by" VALUE ="Session runs"/>
        <ATTRIBUTE NAME ="Save session log for these runs" VALUE ="9"/>
        <ATTRIBUTE NAME ="Session Log File Max Size" VALUE ="0"/>
        <ATTRIBUTE NAME ="Session Log File Max Time Period" VALUE ="0"/>
        <ATTRIBUTE NAME ="Maximum Partial Session Log Files" VALUE ="1"/>
        <ATTRIBUTE NAME ="Writer Commit Statistics Log Frequency" VALUE ="1"/>
        <ATTRIBUTE NAME ="Writer Commit Statistics Log Interval" VALUE ="0"/>
        <ATTRIBUTE NAME ="Error handling" VALUE =""/>
        <ATTRIBUTE NAME ="Stop on errors" VALUE ="1"/>
        <ATTRIBUTE NAME ="Override tracing" VALUE ="None"/>
        <ATTRIBUTE NAME ="On Stored Procedure error" VALUE ="Stop"/>
        <ATTRIBUTE NAME ="On Pre-session command task error" VALUE ="Stop"/>
        <ATTRIBUTE NAME ="On Pre-Post SQL error" VALUE ="Stop"/>
        <ATTRIBUTE NAME ="Enable Recovery" VALUE ="NO"/>
        <ATTRIBUTE NAME ="Error Log Type" VALUE ="None"/>
        <ATTRIBUTE NAME ="Error Log Table Name Prefix" VALUE =""/>
        <ATTRIBUTE NAME ="Error Log File Name" VALUE ="PMError.log"/>
        <ATTRIBUTE NAME ="Log Source Row Data" VALUE ="NO"/>
        <ATTRIBUTE NAME ="Data Column Delimiter" VALUE ="|"/>
        <ATTRIBUTE NAME ="Partitioning Options" VALUE =""/>
        <ATTRIBUTE NAME ="Dynamic Partitioning" VALUE ="Disabled"/>
        <ATTRIBUTE NAME ="Number of Partitions" VALUE ="1"/>
        <ATTRIBUTE NAME ="Multiplication Factor" VALUE ="Auto"/>
        <ATTRIBUTE NAME ="Session on Grid" VALUE =""/>
        <ATTRIBUTE NAME ="Is Enabled" VALUE ="NO"/>
    </CONFIG>
    <SESSION DESCRIPTION ="Session to execute the mapping that loads data in STG_UW_WIP_OPP1040 from OPP1040 " ISVALID ="YES" MAPPINGNAME ="m_STG_UW_WIP_OPP1040" NAME ="s_m_STG_UW_WIP_OPP1040" REUSABLE ="YES" SORTORDER ="Binary" VERSIONNUMBER ="1">
        <SESSTRANSFORMATIONINST ISREPARTITIONPOINT ="YES" PARTITIONTYPE ="PASS THROUGH" PIPELINE ="1" SINSTANCENAME ="STG_UW_WIP_OPP1040" STAGE ="1" TRANSFORMATIONNAME ="STG_UW_WIP_OPP1040" TRANSFORMATIONTYPE ="Target Definition">
            <ATTRIBUTE NAME ="Table Name Prefix" VALUE ="STAGING"/>
        </SESSTRANSFORMATIONINST>
        <SESSTRANSFORMATIONINST ISREPARTITIONPOINT ="NO" PIPELINE ="1" SINSTANCENAME ="EXP_STG_UW_WIP_OPP1040" STAGE ="2" TRANSFORMATIONNAME ="EXP_STG_UW_WIP_OPP1040" TRANSFORMATIONTYPE ="Expression">
            <PARTITION DESCRIPTION ="" NAME ="Partition #1"/>
        </SESSTRANSFORMATIONINST>
        <SESSTRANSFORMATIONINST ISREPARTITIONPOINT ="NO" PIPELINE ="0" SINSTANCENAME ="OPP1040" STAGE ="0" TRANSFORMATIONNAME ="OPP1040" TRANSFORMATIONTYPE ="Source Definition"/>
        <SESSTRANSFORMATIONINST ISREPARTITIONPOINT ="YES" PARTITIONTYPE ="PASS THROUGH" PIPELINE ="1" SINSTANCENAME ="SQ_OPP1040" STAGE ="2" TRANSFORMATIONNAME ="SQ_OPP1040" TRANSFORMATIONTYPE ="Source Qualifier"/>
        <CONFIGREFERENCE REFOBJECTNAME ="default_session_config" TYPE ="Session config">
            <ATTRIBUTE NAME ="Save session log for these runs" VALUE ="9"/>
            <ATTRIBUTE NAME ="Stop on errors" VALUE ="1"/>
        </CONFIGREFERENCE>
        <SESSIONEXTENSION NAME ="Relational Writer" SINSTANCENAME ="STG_UW_WIP_OPP1040" SUBTYPE ="Relational Writer" TRANSFORMATIONTYPE ="Target Definition" TYPE ="WRITER">
            <CONNECTIONREFERENCE CNXREFNAME ="DB Connection" CONNECTIONNAME ="SLBADW" CONNECTIONNUMBER ="1" CONNECTIONSUBTYPE ="Oracle" CONNECTIONTYPE ="Relational" VARIABLE =""/>
            <ATTRIBUTE NAME ="Target load type" VALUE ="Normal"/>
            <ATTRIBUTE NAME ="Insert" VALUE ="YES"/>
            <ATTRIBUTE NAME ="Update as Update" VALUE ="YES"/>
            <ATTRIBUTE NAME ="Update as Insert" VALUE ="NO"/>
            <ATTRIBUTE NAME ="Update else Insert" VALUE ="NO"/>
            <ATTRIBUTE NAME ="Delete" VALUE ="NO"/>
            <ATTRIBUTE NAME ="Truncate target table option" VALUE ="YES"/>
            <ATTRIBUTE NAME ="Reject file directory" VALUE ="$PMBadFileDir&#x5c;SUPPLY_CHAIN_BI&#x5c;BAD&#x5c;"/>
            <ATTRIBUTE NAME ="Reject filename" VALUE ="s_m_STG_UW_WIP_OPP1040.bad"/>
        </SESSIONEXTENSION>
        <SESSIONEXTENSION DSQINSTNAME ="SQ_OPP1040" DSQINSTTYPE ="Source Qualifier" NAME ="Relational Reader" SINSTANCENAME ="OPP1040" SUBTYPE ="Relational Reader" TRANSFORMATIONTYPE ="Source Definition" TYPE ="READER"/>
        <SESSIONEXTENSION NAME ="Relational Reader" SINSTANCENAME ="SQ_OPP1040" SUBTYPE ="Relational Reader" TRANSFORMATIONTYPE ="Source Qualifier" TYPE ="READER">
            <CONNECTIONREFERENCE CNXREFNAME ="DB Connection" CONNECTIONNAME ="hq400U" CONNECTIONNUMBER ="1" CONNECTIONSUBTYPE ="ODBC" CONNECTIONTYPE ="Relational" VARIABLE =""/>
        </SESSIONEXTENSION>
        <ATTRIBUTE NAME ="General Options" VALUE =""/>
        <ATTRIBUTE NAME ="Write Backward Compatible Session Log File" VALUE ="YES"/>
        <ATTRIBUTE NAME ="Session Log File Name" VALUE ="s_m_STG_UW_WIP_OPP1040.log"/>
        <ATTRIBUTE NAME ="Session Log File directory" VALUE ="$PMSessionLogDir&#x5c;SUPPLY_CHAIN_BI&#x5c;LOG&#x5c;"/>
        <ATTRIBUTE NAME ="Parameter Filename" VALUE =""/>
        <ATTRIBUTE NAME ="Enable Test Load" VALUE ="NO"/>
        <ATTRIBUTE NAME ="$Source connection value" VALUE =""/>
        <ATTRIBUTE NAME ="$Target connection value" VALUE =""/>
        <ATTRIBUTE NAME ="Treat source rows as" VALUE ="Insert"/>
        <ATTRIBUTE NAME ="Commit Type" VALUE ="Target"/>
        <ATTRIBUTE NAME ="Commit Interval" VALUE ="2000000"/>
        <ATTRIBUTE NAME ="Commit On End Of File" VALUE ="YES"/>
        <ATTRIBUTE NAME ="Rollback Transactions on Errors" VALUE ="NO"/>
        <ATTRIBUTE NAME ="Recovery Strategy" VALUE ="Restart task"/>
        <ATTRIBUTE NAME ="Java Classpath" VALUE =""/>
        <ATTRIBUTE NAME ="Performance" VALUE =""/>
        <ATTRIBUTE NAME ="DTM buffer size" VALUE ="Auto"/>
        <ATTRIBUTE NAME ="Collect performance data" VALUE ="NO"/>
        <ATTRIBUTE NAME ="Write performance data to repository" VALUE ="NO"/>
        <ATTRIBUTE NAME ="Incremental Aggregation" VALUE ="NO"/>
        <ATTRIBUTE NAME ="Enable high precision" VALUE ="NO"/>
        <ATTRIBUTE NAME ="Session retry on deadlock" VALUE ="NO"/>
        <ATTRIBUTE NAME ="Pushdown Optimization" VALUE ="None"/>
        <ATTRIBUTE NAME ="Allow Temporary View for Pushdown" VALUE ="NO"/>
        <ATTRIBUTE NAME ="Allow Temporary Sequence for Pushdown" VALUE ="NO"/>
        <ATTRIBUTE NAME ="Allow Pushdown for User Incompatible Connections" VALUE ="NO"/>
        <METADATAEXTENSION DATATYPE ="STRING" DESCRIPTION ="Conversion Mapping  Name with version " DOMAINNAME ="User Defined Metadata Domain" ISCLIENTEDITABLE ="YES" ISCLIENTVISIBLE ="YES" ISREUSABLE ="NO" ISSHAREREAD ="NO" ISSHAREWRITE ="NO" MAXLENGTH ="256" NAME ="CONV_MAP_NAME" VALUE ="09/24/2009:moraffee:Conversion Mapping - UW WIP OPP1040_v1.0.xls" VENDORNAME ="INFORMATICA"/>
    </SESSION>
    <WORKFLOW DESCRIPTION ="Workflow to execute the session that load in STG_UW_WIP_OPP1040 from OPP1040 " ISENABLED ="YES" ISRUNNABLESERVICE ="NO" ISSERVICE ="NO" ISVALID ="YES" NAME ="wf_s_m_STG_UW_WIP_OPP1040" REUSABLE_SCHEDULER ="NO" SCHEDULERNAME ="Scheduler" SERVERNAME ="Domain10_PRD_Int_Svc" SERVER_DOMAINNAME ="Domain10_PRD" SUSPEND_ON_ERROR ="NO" TASKS_MUST_RUN_ON_SERVER ="NO" VERSIONNUMBER ="1">
        <SCHEDULER DESCRIPTION ="" NAME ="Scheduler" REUSABLE ="NO" VERSIONNUMBER ="1">
            <SCHEDULEINFO SCHEDULETYPE ="ONDEMAND"/>
        </SCHEDULER>
        <TASK DESCRIPTION ="" NAME ="Start" REUSABLE ="NO" TYPE ="Start" VERSIONNUMBER ="1"/>
        <TASKINSTANCE DESCRIPTION ="Session to execute the mapping that loads data in STG_UW_WIP_OPP1040 from OPP1040 " FAIL_PARENT_IF_INSTANCE_DID_NOT_RUN ="YES" FAIL_PARENT_IF_INSTANCE_FAILS ="YES" ISENABLED ="YES" NAME ="s_m_STG_UW_WIP_OPP1040" REUSABLE ="YES" TASKNAME ="s_m_STG_UW_WIP_OPP1040" TASKTYPE ="Session" TREAT_INPUTLINK_AS_AND ="NO"/>
        <TASKINSTANCE DESCRIPTION ="" ISENABLED ="YES" NAME ="Start" REUSABLE ="NO" TASKNAME ="Start" TASKTYPE ="Start"/>
        <WORKFLOWLINK CONDITION ="" FROMTASK ="Start" TOTASK ="s_m_STG_UW_WIP_OPP1040"/>
        <WORKFLOWVARIABLE DATATYPE ="date/time" DEFAULTVALUE ="" DESCRIPTION ="The time this task started" ISNULL ="NO" ISPERSISTENT ="NO" NAME ="$s_m_STG_UW_WIP_OPP1040.StartTime" USERDEFINED ="NO"/>
        <WORKFLOWVARIABLE DATATYPE ="date/time" DEFAULTVALUE ="" DESCRIPTION ="The time this task completed" ISNULL ="NO" ISPERSISTENT ="NO" NAME ="$s_m_STG_UW_WIP_OPP1040.EndTime" USERDEFINED ="NO"/>
        <WORKFLOWVARIABLE DATATYPE ="integer" DEFAULTVALUE ="" DESCRIPTION ="Status of this task&apos;s execution" ISNULL ="NO" ISPERSISTENT ="NO" NAME ="$s_m_STG_UW_WIP_OPP1040.Status" USERDEFINED ="NO"/>
        <WORKFLOWVARIABLE DATATYPE ="integer" DEFAULTVALUE ="" DESCRIPTION ="Status of the previous task that is not disabled" ISNULL ="NO" ISPERSISTENT ="NO" NAME ="$s_m_STG_UW_WIP_OPP1040.PrevTaskStatus" USERDEFINED ="NO"/>
        <WORKFLOWVARIABLE DATATYPE ="integer" DEFAULTVALUE ="" DESCRIPTION ="Error code for this task&apos;s execution" ISNULL ="NO" ISPERSISTENT ="NO" NAME ="$s_m_STG_UW_WIP_OPP1040.ErrorCode" USERDEFINED ="NO"/>
        <WORKFLOWVARIABLE DATATYPE ="string" DEFAULTVALUE ="" DESCRIPTION ="Error message for this task&apos;s execution" ISNULL ="NO" ISPERSISTENT ="NO" NAME ="$s_m_STG_UW_WIP_OPP1040.ErrorMsg" USERDEFINED ="NO"/>
        <WORKFLOWVARIABLE DATATYPE ="integer" DEFAULTVALUE ="" DESCRIPTION ="Rows successfully read" ISNULL ="NO" ISPERSISTENT ="NO" NAME ="$s_m_STG_UW_WIP_OPP1040.SrcSuccessRows" USERDEFINED ="NO"/>
        <WORKFLOWVARIABLE DATATYPE ="integer" DEFAULTVALUE ="" DESCRIPTION ="Rows failed to read" ISNULL ="NO" ISPERSISTENT ="NO" NAME ="$s_m_STG_UW_WIP_OPP1040.SrcFailedRows" USERDEFINED ="NO"/>
        <WORKFLOWVARIABLE DATATYPE ="integer" DEFAULTVALUE ="" DESCRIPTION ="Rows successfully loaded" ISNULL ="NO" ISPERSISTENT ="NO" NAME ="$s_m_STG_UW_WIP_OPP1040.TgtSuccessRows" USERDEFINED ="NO"/>
        <WORKFLOWVARIABLE DATATYPE ="integer" DEFAULTVALUE ="" DESCRIPTION ="Rows failed to load" ISNULL ="NO" ISPERSISTENT ="NO" NAME ="$s_m_STG_UW_WIP_OPP1040.TgtFailedRows" USERDEFINED ="NO"/>
        <WORKFLOWVARIABLE DATATYPE ="integer" DEFAULTVALUE ="" DESCRIPTION ="Total number of transformation errors" ISNULL ="NO" ISPERSISTENT ="NO" NAME ="$s_m_STG_UW_WIP_OPP1040.TotalTransErrors" USERDEFINED ="NO"/>
        <WORKFLOWVARIABLE DATATYPE ="integer" DEFAULTVALUE ="" DESCRIPTION ="First error code" ISNULL ="NO" ISPERSISTENT ="NO" NAME ="$s_m_STG_UW_WIP_OPP1040.FirstErrorCode" USERDEFINED ="NO"/>
        <WORKFLOWVARIABLE DATATYPE ="string" DEFAULTVALUE ="" DESCRIPTION ="First error message" ISNULL ="NO" ISPERSISTENT ="NO" NAME ="$s_m_STG_UW_WIP_OPP1040.FirstErrorMsg" USERDEFINED ="NO"/>
        <WORKFLOWVARIABLE DATATYPE ="date/time" DEFAULTVALUE ="" DESCRIPTION ="The time this task started" ISNULL ="NO" ISPERSISTENT ="NO" NAME ="$Start.StartTime" USERDEFINED ="NO"/>
        <WORKFLOWVARIABLE DATATYPE ="date/time" DEFAULTVALUE ="" DESCRIPTION ="The time this task completed" ISNULL ="NO" ISPERSISTENT ="NO" NAME ="$Start.EndTime" USERDEFINED ="NO"/>
        <WORKFLOWVARIABLE DATATYPE ="integer" DEFAULTVALUE ="" DESCRIPTION ="Status of this task&apos;s execution" ISNULL ="NO" ISPERSISTENT ="NO" NAME ="$Start.Status" USERDEFINED ="NO"/>
        <WORKFLOWVARIABLE DATATYPE ="integer" DEFAULTVALUE ="" DESCRIPTION ="Status of the previous task that is not disabled" ISNULL ="NO" ISPERSISTENT ="NO" NAME ="$Start.PrevTaskStatus" USERDEFINED ="NO"/>
        <WORKFLOWVARIABLE DATATYPE ="integer" DEFAULTVALUE ="" DESCRIPTION ="Error code for this task&apos;s execution" ISNULL ="NO" ISPERSISTENT ="NO" NAME ="$Start.ErrorCode" USERDEFINED ="NO"/>
        <WORKFLOWVARIABLE DATATYPE ="string" DEFAULTVALUE ="" DESCRIPTION ="Error message for this task&apos;s execution" ISNULL ="NO" ISPERSISTENT ="NO" NAME ="$Start.ErrorMsg" USERDEFINED ="NO"/>
        <ATTRIBUTE NAME ="Parameter Filename" VALUE =""/>
        <ATTRIBUTE NAME ="Write Backward Compatible Workflow Log File" VALUE ="YES"/>
        <ATTRIBUTE NAME ="Workflow Log File Name" VALUE ="wf_s_m_STG_UW_WIP_OPP1040.log"/>
        <ATTRIBUTE NAME ="Workflow Log File Directory" VALUE ="$PMWorkflowLogDir&#x5c;SUPPLY_CHAIN_BI&#x5c;LOG&#x5c;"/>
        <ATTRIBUTE NAME ="Save Workflow log by" VALUE ="By runs"/>
        <ATTRIBUTE NAME ="Save workflow log for these runs" VALUE ="9"/>
        <ATTRIBUTE NAME ="Service Name" VALUE =""/>
        <ATTRIBUTE NAME ="Service Timeout" VALUE ="0"/>
        <ATTRIBUTE NAME ="Is Service Visible" VALUE ="NO"/>
        <ATTRIBUTE NAME ="Is Service Protected" VALUE ="NO"/>
        <ATTRIBUTE NAME ="Fail task after wait time" VALUE ="0"/>
        <ATTRIBUTE NAME ="Enable HA recovery" VALUE ="NO"/>
        <ATTRIBUTE NAME ="Automatically recover terminated tasks" VALUE ="NO"/>
        <ATTRIBUTE NAME ="Service Level Name" VALUE ="Default"/>
        <ATTRIBUTE NAME ="Allow concurrent run with unique run instance name" VALUE ="NO"/>
        <ATTRIBUTE NAME ="Allow concurrent run with same run instance name" VALUE ="NO"/>
        <ATTRIBUTE NAME ="Maximum number of concurrent runs" VALUE ="0"/>
        <ATTRIBUTE NAME ="Assigned Web Services Hubs" VALUE =""/>
        <ATTRIBUTE NAME ="Maximum number of concurrent runs per Hub" VALUE ="1000"/>
        <ATTRIBUTE NAME ="Expected Service Time" VALUE ="1"/>
        <METADATAEXTENSION DATATYPE ="STRING" DESCRIPTION ="Conversion Mapping Name with version " DOMAINNAME ="User Defined Metadata Domain" ISCLIENTEDITABLE ="YES" ISCLIENTVISIBLE ="YES" ISREUSABLE ="NO" ISSHAREREAD ="NO" ISSHAREWRITE ="NO" MAXLENGTH ="256" NAME ="CONV_MAP_NAME" VALUE ="09/24/2009:moraffee:Conversion Mapping - UW WIP OPP1040_v1.0.xls" VENDORNAME ="INFORMATICA"/>
        <METADATAEXTENSION DATATYPE ="STRING" DESCRIPTION ="" DOMAINNAME ="User Defined Metadata Domain" ISCLIENTEDITABLE ="YES" ISCLIENTVISIBLE ="YES" ISREUSABLE ="NO" ISSHAREREAD ="NO" ISSHAREWRITE ="NO" MAXLENGTH ="256" NAME ="Extension" VALUE ="CM - MarginLoss - stgMarginLossExpenseToStgFactSalesNew v1.0" VENDORNAME ="INFORMATICA"/>
    </WORKFLOW>
</FOLDER>
</REPOSITORY>
</POWERMART>