{
  "definitions": {
    "ZV_DWC_STO": {
      "kind": "entity",
      "elements": {
        "KUNNR": {
          "@EndUserText.label": "Recipient",
          "type": "cds.String",
          "length": 10,
          "@DataWarehouse.native.dataType": "NVARCHAR",
          "@DataWarehouse.capabilities.filter.allowedExpressions": [
            {
              "#": "EQUAL"
            },
            {
              "#": "LIKE"
            },
            {
              "#": "BETWEEN"
            }
          ],
          "key": true,
          "notNull": true
        },
        "MATNR": {
          "@EndUserText.label": "Material Number",
          "type": "cds.String",
          "length": 40,
          "@DataWarehouse.native.dataType": "NVARCHAR",
          "@DataWarehouse.capabilities.filter.allowedExpressions": [
            {
              "#": "EQUAL"
            },
            {
              "#": "LIKE"
            },
            {
              "#": "BETWEEN"
            }
          ],
          "key": true,
          "notNull": true
        },
        "SOBST": {
          "@EndUserText.label": "Target stock at recipient",
          "precision": 17,
          "scale": 3,
          "type": "cds.Decimal",
          "@DataWarehouse.native.dataType": "DECIMAL",
          "@DataWarehouse.capabilities.filter.allowedExpressions": [
            {
              "#": "EQUAL"
            },
            {
              "#": "BETWEEN"
            }
          ]
        },
        "AVAILABLE_STOCK": {
          "@EndUserText.label": "AVAILABLE_STOCK",
          "precision": 17,
          "scale": 3,
          "type": "cds.Decimal",
          "@DataWarehouse.native.dataType": "DECIMAL",
          "@DataWarehouse.capabilities.filter.allowedExpressions": [
            {
              "#": "EQUAL"
            },
            {
              "#": "BETWEEN"
            }
          ]
        },
        "DWERK": {
          "@EndUserText.label": "Delivering Plant (Own or External)",
          "type": "cds.String",
          "length": 4,
          "@DataWarehouse.native.dataType": "NVARCHAR",
          "@DataWarehouse.capabilities.filter.allowedExpressions": [
            {
              "#": "EQUAL"
            },
            {
              "#": "LIKE"
            },
            {
              "#": "BETWEEN"
            }
          ]
        },
        "AVAILABLE_STOCK_DC": {
          "@EndUserText.label": "AVAILABLE_STOCK_DC",
          "precision": 17,
          "scale": 3,
          "type": "cds.Decimal",
          "@DataWarehouse.native.dataType": "DECIMAL",
          "@DataWarehouse.capabilities.filter.allowedExpressions": [
            {
              "#": "EQUAL"
            },
            {
              "#": "BETWEEN"
            }
          ]
        },
        "NET_DEMAND": {
          "@EndUserText.label": "NET_DEMAND",
          "precision": 17,
          "scale": 3,
          "type": "cds.Decimal",
          "@DataWarehouse.native.dataType": "DECIMAL",
          "@DataWarehouse.capabilities.filter.allowedExpressions": [
            {
              "#": "EQUAL"
            },
            {
              "#": "BETWEEN"
            }
          ]
        },
        "CREATED_ON": {
          "@EndUserText.label": "Created On",
          "type": "cds.String",
          "length": 8,
          "@DataWarehouse.native.dataType": "VARCHAR",
          "@DataWarehouse.capabilities.filter.allowedExpressions": [
            {
              "#": "EQUAL"
            },
            {
              "#": "LIKE"
            },
            {
              "#": "BETWEEN"
            }
          ]
        },
        "CREATED_AT_TIME": {
          "@EndUserText.label": "Time of Creation",
          "type": "cds.String",
          "length": 6,
          "@DataWarehouse.native.dataType": "VARCHAR",
          "@DataWarehouse.capabilities.filter.allowedExpressions": [
            {
              "#": "EQUAL"
            },
            {
              "#": "LIKE"
            },
            {
              "#": "BETWEEN"
            }
          ]
        },
        "CHANGED_ON": {
          "@EndUserText.label": "CHANGED_ON",
          "type": "cds.String",
          "length": 8,
          "@DataWarehouse.native.dataType": "VARCHAR",
          "@DataWarehouse.capabilities.filter.allowedExpressions": [
            {
              "#": "EQUAL"
            },
            {
              "#": "LIKE"
            },
            {
              "#": "BETWEEN"
            }
          ]
        },
        "CHANGED_AT_TIME": {
          "@EndUserText.label": "Time of last change",
          "type": "cds.String",
          "length": 6,
          "@DataWarehouse.native.dataType": "VARCHAR",
          "@DataWarehouse.capabilities.filter.allowedExpressions": [
            {
              "#": "EQUAL"
            },
            {
              "#": "LIKE"
            },
            {
              "#": "BETWEEN"
            }
          ]
        },
        "CREATED_BY": {
          "@EndUserText.label": "Name of Person who Created the Object",
          "type": "cds.String",
          "length": 12,
          "@DataWarehouse.native.dataType": "NVARCHAR",
          "@DataWarehouse.capabilities.filter.allowedExpressions": [
            {
              "#": "EQUAL"
            },
            {
              "#": "LIKE"
            },
            {
              "#": "BETWEEN"
            }
          ]
        },
        "CHANGED_BY": {
          "@EndUserText.label": "Name of person who changed object",
          "type": "cds.String",
          "length": 12,
          "@DataWarehouse.native.dataType": "NVARCHAR",
          "@DataWarehouse.capabilities.filter.allowedExpressions": [
            {
              "#": "EQUAL"
            },
            {
              "#": "LIKE"
            },
            {
              "#": "BETWEEN"
            }
          ]
        }
      },
      "@ObjectModel.supportedCapabilities": [
        {
          "#": "SQL_DATA_SOURCE"
        },
        {
          "#": "DATA_STRUCTURE"
        }
      ],
      "@EndUserText.label": "Net demand for Material in Store",
      "@ObjectModel.modelingPattern": {
        "#": "DATA_STRUCTURE"
      },
      "@DataWarehouse.remote.connection": "SAP_S4_AB",
      "@DataWarehouse.remote.entity": "ABAP_CDS.ZV_DWC_STO$F"
    }
  },
  "version": {
    "csn": "1.0"
  },
  "meta": {
    "creator": "CDS Compiler v1.19.2"
  },
  "$version": "1.0"
}